Workbook
Name Slicer_Sub_Category: #N/A
Name Slicer_Sub_Category1: #N/A
Name Slicer_Year: #N/A

Sheet Dashboard
B8: 2019-20
D10: =VLOOKUP(B8,'Analytics and main data'!$A:$H,2,0) -> 1948083.5 | H10: =VLOOKUP(B8,'Analytics and main data'!$A:$H,3,0) -> 2615319.7 | M10: =VLOOKUP(B8,'Analytics and main data'!$A:$H,5,0) -> 7370383.5 | R10: =VLOOKUP(B8,'Analytics and main data'!$A:$H,6,0) -> 6759434.7 | W10: =VLOOKUP(B8,'Analytics and main data'!$A:$H,8,0) -> 0.078396639
E115: Visit Detailed Report
E121: Source Data

Sheet Report

Sheet Analytics and main data
B1: ANALYTICS : Revenue & Capital: Totals, Deficit/Surplus, Growth % ( ₹ in Crore)
A2: Year | B2: Revenue Receipts (₹Cr) | C2: Revenue Expenditure (₹Cr) | D2: Revenue Deficit (₹Cr) | E2: Capital Receipts (₹Cr) | F2: Capital Expenditure (₹Cr) | G2: Capital Surplus (₹Cr) | H2: Rev Growth % | I2: Trend
A3: 2013-14 | B3: ='Main Data'!C3 -> 1217798.8 | C3: ='Main Data'!C16 -> 1575096.6 | D3: =(Table2[[#This Row],[Revenue Expenditure (₹Cr)]]-Table2[[#This Row],[Revenue Receipts (₹Cr)]])*-1 -> -357297.78 | E3: ='Main Data'!C29 -> 4048883.1 | F3: ='Main Data'!C42 -> 3711135.7 | G3: =Table2[[#This Row],[Capital Receipts (₹Cr)]]-Table2[[#This Row],[Capital Expenditure (₹Cr)]] -> 337747.4 | H3: - | I3: Base year
A4: 2014-15 | B4: ='Main Data'!C4 -> 1328909 | C4: ='Main Data'!C17 -> 1695136.8 | D4: =(Table2[[#This Row],[Revenue Expenditure (₹Cr)]]-Table2[[#This Row],[Revenue Receipts (₹Cr)]])*-1 -> -366227.83 | E4: ='Main Data'!C30 -> 4282482.8 | F4: ='Main Data'!C43 -> 3921706.2 | G4: =Table2[[#This Row],[Capital Receipts (₹Cr)]]-Table2[[#This Row],[Capital Expenditure (₹Cr)]] -> 360776.61 | H4: =(Table2[[#This Row],[Revenue Receipts (₹Cr)]]-B3)/B3 -> 0.091238529 | I4: =IF(Table2[[#This Row],[Revenue Receipts (₹Cr)]]>B3,"▲Growth","▼ Decline") -> ▲Growth
A5: 2015-16 | B5: ='Main Data'!C5 -> 1436160.2 | C5: ='Main Data'!C18 -> 1779528.8 | D5: =(Table2[[#This Row],[Revenue Expenditure (₹Cr)]]-Table2[[#This Row],[Revenue Receipts (₹Cr)]])*-1 -> -343368.59 | E5: ='Main Data'!C31 -> 4400951.2 | F5: ='Main Data'!C44 -> 4063795.2 | G5: =Table2[[#This Row],[Capital Receipts (₹Cr)]]-Table2[[#This Row],[Capital Expenditure (₹Cr)]] -> 337155.96 | H5: =(Table2[[#This Row],[Revenue Receipts (₹Cr)]]-B4)/B4 -> 0.080706251 | I5: =IF(Table2[[#This Row],[Revenue Receipts (₹Cr)]]>B4,"▲Growth","▼ Decline") -> ▲Growth
A6: 2016-17 | B6: ='Main Data'!C6 -> 1615988 | C6: ='Main Data'!C19 -> 1933018.1 | D6: =(Table2[[#This Row],[Revenue Expenditure (₹Cr)]]-Table2[[#This Row],[Revenue Receipts (₹Cr)]])*-1 -> -317030.08 | E6: ='Main Data'!C32 -> 6222850.2 | F6: ='Main Data'!C45 -> 5988306.4 | G6: =Table2[[#This Row],[Capital Receipts (₹Cr)]]-Table2[[#This Row],[Capital Expenditure (₹Cr)]] -> 234543.83 | H6: =(Table2[[#This Row],[Revenue Receipts (₹Cr)]]-B5)/B5 -> 0.12521427 | I6: =IF(Table2[[#This Row],[Revenue Receipts (₹Cr)]]>B5,"▲Growth","▼ Decline") -> ▲Growth
A7: 2017-18 | B7: ='Main Data'!C7 -> 1691143.1 | C7: ='Main Data'!C20 -> 2140084.5 | D7: =(Table2[[#This Row],[Revenue Expenditure (₹Cr)]]-Table2[[#This Row],[Revenue Receipts (₹Cr)]])*-1 -> -448941.43 | E7: ='Main Data'!C33 -> 6724689.2 | F7: ='Main Data'!C46 -> 6279856.8 | G7: =Table2[[#This Row],[Capital Receipts (₹Cr)]]-Table2[[#This Row],[Capital Expenditure (₹Cr)]] -> 444832.38 | H7: =(Table2[[#This Row],[Revenue Receipts (₹Cr)]]-B6)/B6 -> 0.046507227 | I7: =IF(Table2[[#This Row],[Revenue Receipts (₹Cr)]]>B6,"▲Growth","▼ Decline") -> ▲Growth
A8: 2018-19 | B8: ='Main Data'!C8 -> 1806462.9 | C8: ='Main Data'!C21 -> 2261570.8 | D8: =(Table2[[#This Row],[Revenue Expenditure (₹Cr)]]-Table2[[#This Row],[Revenue Receipts (₹Cr)]])*-1 -> -455107.9 | E8: ='Main Data'!C34 -> 6883718.4 | F8: ='Main Data'!C47 -> 6519135.6 | G8: =Table2[[#This Row],[Capital Receipts (₹Cr)]]-Table2[[#This Row],[Capital Expenditure (₹Cr)]] -> 364582.81 | H8: =(Table2[[#This Row],[Revenue Receipts (₹Cr)]]-B7)/B7 -> 0.068190451 | I8: =IF(Table2[[#This Row],[Revenue Receipts (₹Cr)]]>B7,"▲Growth","▼ Decline") -> ▲Growth
A9: 2019-20 | B9: ='Main Data'!C9 -> 1948083.5 | C9: ='Main Data'!C22 -> 2615319.7 | D9: =(Table2[[#This Row],[Revenue Expenditure (₹Cr)]]-Table2[[#This Row],[Revenue Receipts (₹Cr)]])*-1 -> -667236.14 | E9: ='Main Data'!C35 -> 7370383.5 | F9: ='Main Data'!C48 -> 6759434.7 | G9: =Table2[[#This Row],[Capital Receipts (₹Cr)]]-Table2[[#This Row],[Capital Expenditure (₹Cr)]] -> 610948.82 | H9: =(Table2[[#This Row],[Revenue Receipts (₹Cr)]]-B8)/B8 -> 0.078396639 | I9: =IF(Table2[[#This Row],[Revenue Receipts (₹Cr)]]>B8,"▲Growth","▼ Decline") -> ▲Growth
A10: 2020-21 | B10: ='Main Data'!C10 -> 1864513.5 | C10: ='Main Data'!C23 -> 3314851.9 | D10: =(Table2[[#This Row],[Revenue Expenditure (₹Cr)]]-Table2[[#This Row],[Revenue Receipts (₹Cr)]])*-1 -> -1450338.4 | E10: ='Main Data'!C36 -> 8230730.1 | F10: ='Main Data'!C49 -> 6777429.7 | G10: =Table2[[#This Row],[Capital Receipts (₹Cr)]]-Table2[[#This Row],[Capital Expenditure (₹Cr)]] -> 1453300.4 | H10: =(Table2[[#This Row],[Revenue Receipts (₹Cr)]]-B9)/B9 -> -0.042898602 | I10: =IF(Table2[[#This Row],[Revenue Receipts (₹Cr)]]>B9,"▲Growth","▼ Decline") -> ▼ Decline
A11: 2021-22 | B11: ='Main Data'!C11 -> 2436421.5 | C11: ='Main Data'!C24 -> 3468188.8 | D11: =(Table2[[#This Row],[Revenue Expenditure (₹Cr)]]-Table2[[#This Row],[Revenue Receipts (₹Cr)]])*-1 -> -1031767.3 | E11: ='Main Data'!C37 -> 8288738 | F11: ='Main Data'!C50 -> 7445313 | G11: =Table2[[#This Row],[Capital Receipts (₹Cr)]]-Table2[[#This Row],[Capital Expenditure (₹Cr)]] -> 843424.92 | H11: =(Table2[[#This Row],[Revenue Receipts (₹Cr)]]-B10)/B10 -> 0.30673311 | I11: =IF(Table2[[#This Row],[Revenue Receipts (₹Cr)]]>B10,"▲Growth","▼ Decline") -> ▲Growth
A12: 2022-23 | B12: ='Main Data'!C12 -> 2713267.2 | C12: ='Main Data'!C25 -> 3783698.5 | D12: =(Table2[[#This Row],[Revenue Expenditure (₹Cr)]]-Table2[[#This Row],[Revenue Receipts (₹Cr)]])*-1 -> -1070431.3 | E12: ='Main Data'!C38 -> 8947200.1 | F12: ='Main Data'!C51 -> 7966516.6 | G12: =Table2[[#This Row],[Capital Receipts (₹Cr)]]-Table2[[#This Row],[Capital Expenditure (₹Cr)]] -> 980683.53 | H12: =(Table2[[#This Row],[Revenue Receipts (₹Cr)]]-B11)/B11 -> 0.11362801 | I12: =IF(Table2[[#This Row],[Revenue Receipts (₹Cr)]]>B11,"▲Growth","▼ Decline") -> ▲Growth
A13: 2023-24 | B13: ='Main Data'!C13 -> 3088174.6 | C13: ='Main Data'!C26 -> 3854082.2 | D13: =(Table2[[#This Row],[Revenue Expenditure (₹Cr)]]-Table2[[#This Row],[Revenue Receipts (₹Cr)]])*-1 -> -765907.57 | E13: ='Main Data'!C39 -> 9322304.2 | F13: ='Main Data'!C52 -> 8460982.9 | G13: =Table2[[#This Row],[Capital Receipts (₹Cr)]]-Table2[[#This Row],[Capital Expenditure (₹Cr)]] -> 861321.3 | H13: =(Table2[[#This Row],[Revenue Receipts (₹Cr)]]-B12)/B12 -> 0.13817564 | I13: =IF(Table2[[#This Row],[Revenue Receipts (₹Cr)]]>B12,"▲Growth","▼ Decline") -> ▲Growth
A14: RE 2024-25 | B14: ='Main Data'!C14 -> 3485869.3 | C14: ='Main Data'!C27 -> 4096607.1 | D14: =(Table2[[#This Row],[Revenue Expenditure (₹Cr)]]-Table2[[#This Row],[Revenue Receipts (₹Cr)]])*-1 -> -610737.78 | E14: ='Main Data'!C40 -> 9929531.9 | F14: ='Main Data'!C53 -> 9500416.3 | G14: =Table2[[#This Row],[Capital Receipts (₹Cr)]]-Table2[[#This Row],[Capital Expenditure (₹Cr)]] -> 429115.6 | H14: =(Table2[[#This Row],[Revenue Receipts (₹Cr)]]-B13)/B13 -> 0.12877984 | I14: =IF(Table2[[#This Row],[Revenue Receipts (₹Cr)]]>B13,"▲Growth","▼ Decline") -> ▲Growth
A15: BE 2025-26 | B15: ='Main Data'!C15 -> 3835268.5 | C15: ='Main Data'!C28 -> 4359702.4 | D15: =(Table2[[#This Row],[Revenue Expenditure (₹Cr)]]-Table2[[#This Row],[Revenue Receipts (₹Cr)]])*-1 -> -524433.89 | E15: ='Main Data'!C41 -> 10760099 | F15: ='Main Data'!C54 -> 10293122 | G15: =Table2[[#This Row],[Capital Receipts (₹Cr)]]-Table2[[#This Row],[Capital Expenditure (₹Cr)]] -> 466976.28 | H15: =(Table2[[#This Row],[Revenue Receipts (₹Cr)]]-B14)/B14 -> 0.10023303 | I15: =IF(Table2[[#This Row],[Revenue Receipts (₹Cr)]]>B14,"▲Growth","▼ Decline") -> ▲Growth
A16: Total | B16: =SUM(B3:B15) -> 28468060 | C16: =SUM(C3:C15) -> 36876886 | D16: =SUM(D3:D15) -> -8408826.1 | E16: =SUM(E3:E15) -> 95412561 | F16: =SUM(F3:F15) -> 87687152 | G16: =SUM(G3:G15) -> 7725409.9 | H16: ="-" -> - | I16: ="13 years " -> 13 years

Sheet  Receipts vs Expenditure
A1: Pivot 1 - Receipts vs Expenditure Over Time (₹ Crore)
A2: Years | B2: Revenue Receipts (₹Crore) | C2: Revenue Expenditure (₹Crore) | D2: Capital Expenditure (₹Crore) | E2: Capital Receipts (₹Crore)
A3: 2013-14 | B3: 1217798.8 | C3: 1575096.6 | D3: 3711135.7 | E3: 4048883.1
A4: 2014-15 | B4: 1328909 | C4: 1695136.8 | D4: 3921706.2 | E4: 4282482.8
A5: 2015-16 | B5: 1436160.2 | C5: 1779528.8 | D5: 4063795.2 | E5: 4400951.2
A6: 2016-17 | B6: 1615988 | C6: 1933018.1 | D6: 5988306.4 | E6: 6222850.2 | AX6: Revenue Receipts (₹Crore) | AY6: =VLOOKUP(Dashboard!$B$8,'Analytics and main data'!$A:$H,2,0) -> 1948083.5
A7: 2017-18 | B7: 1691143.1 | C7: 2140084.5 | D7: 6279856.8 | E7: 6724689.2 | AX7: Revenue Expenditure (₹Crore) | AY7: =VLOOKUP(Dashboard!$B$8,'Analytics and main data'!$A:$H,3,0) -> 2615319.7
A8: 2018-19 | B8: 1806462.9 | C8: 2261570.8 | D8: 6519135.6 | E8: 6883718.4 | AX8: Capital Receipts (₹Crore) | AY8: =VLOOKUP(Dashboard!$B$8,'Analytics and main data'!$A:$H,5,0) -> 7370383.5
A9: 2019-20 | B9: 1948083.5 | C9: 2615319.7 | D9: 6759434.7 | E9: 7370383.5 | AX9: Capital Expenditure (₹Crore) | AY9: =VLOOKUP(Dashboard!$B$8,'Analytics and main data'!$A:$H,6,0) -> 6759434.7
A10: 2020-21 | B10: 1864513.5 | C10: 3314851.9 | D10: 6777429.7 | E10: 8230730.1
A11: 2021-22 | B11: 2436421.5 | C11: 3468188.8 | D11: 7445313 | E11: 8288738
A12: 2022-23 | B12: 2713267.2 | C12: 3783698.5 | D12: 7966516.6 | E12: 8947200.1
A13: 2023-24 | B13: 3088174.6 | C13: 3854082.2 | D13: 8460982.9 | E13: 9322304.2
A14: BE 2025-26 | B14: 3835268.5 | C14: 4359702.4 | D14: 10293122 | E14: 10760099
A15: RE 2024-25 | B15: 3485869.3 | C15: 4096607.1 | D15: 9500416.3 | E15: 9929531.9
A16: Grand Total | B16: 28468060 | C16: 36876886 | D16: 87687152 | E16: 95412561

Sheet deficit and surplus
A1: Row Labels | B1: Revenue Deficit(₹Cr) | C1: Capital Surplus(₹Cr)
A2: 2013-14 | B2: -357297.78 | C2: 337747.4
A3: 2014-15 | B3: -366227.83 | C3: 360776.61
A4: 2015-16 | B4: -343368.59 | C4: 337155.96 | G4: Row Labels | H4: Sum of Revenue Deficit (₹Cr) | I4: Sum of Capital Surplus (₹Cr)
A5: 2016-17 | B5: -317030.08 | C5: 234543.83 | G5: 2013-14 | H5: -357297.78 | I5: 337747.4
A6: 2017-18 | B6: -448941.43 | C6: 444832.38 | G6: 2014-15 | H6: -366227.83 | I6: 360776.61
A7: 2018-19 | B7: -455107.9 | C7: 364582.81 | G7: 2015-16 | H7: -343368.59 | I7: 337155.96
A8: 2019-20 | B8: -667236.14 | C8: 610948.82 | G8: 2016-17 | H8: -317030.08 | I8: 234543.83
A9: 2020-21 | B9: -1450338.4 | C9: 1453300.4 | G9: 2017-18 | H9: -448941.43 | I9: 444832.38
A10: 2021-22 | B10: -1031767.3 | C10: 843424.92 | G10: 2018-19 | H10: -455107.9 | I10: 364582.81
A11: 2022-23 | B11: -1070431.3 | C11: 980683.53 | G11: 2019-20 | H11: -667236.14 | I11: 610948.82
A12: 2023-24 | B12: -765907.57 | C12: 861321.3 | G12: 2020-21 | H12: -1450338.4 | I12: 1453300.4
A13: BE 2025-26 | B13: -524433.89 | C13: 466976.28 | G13: 2021-22 | H13: -1031767.3 | I13: 843424.92
A14: RE 2024-25 | B14: -610737.78 | C14: 429115.6 | G14: 2022-23 | H14: -1070431.3 | I14: 980683.53
A15: Grand Total | B15: -8408826.1 | C15: 7725409.9 | G15: 2023-24 | H15: -765907.57 | I15: 861321.3
G16: BE 2025-26 | H16: -524433.89 | I16: 466976.28
G17: RE 2024-25 | H17: -610737.78 | I17: 429115.6

Sheet Tax Revenue composition
B1: Column Labels
A2: Year | B2: CGST | C2: Corporation Tax | D2: Customs | E2: GST Compensation Cess | F2: IGST | G2: Income Tax (excl. Corp Tax) | H2: Securities Transaction Tax | I2: Service Tax | J2: Union Excise Duties | K2: Grand Total
A3: (2013-14) | B3: 0 | C3: 394677.85 | D3: 172085.42 | E3: 0 | F3: 0 | G3: 237817.23 | H3: 5017.5 | I3: 154778.12 | J3: 169455.14 | K3: 1133831.3
A4: (2014-15) | B4: 0 | C4: 428924.74 | D4: 188016.19 | E4: 0 | F4: 0 | G4: 258325.65 | H4: 7398.15 | I4: 167969.04 | J4: 188127.6 | K4: 1238761.4
A5: ( 2015-16) | B5: 0 | C5: 453228.33 | D5: 210338 | E5: 0 | F5: 0 | G5: 280322.5 | H5: 7350.12 | I5: 211414.25 | J5: 287148.55 | K5: 1449801.8
A6: (2016-17) | B6: 0 | C6: 484923.86 | D6: 225370.34 | E6: 0 | F6: 0 | G6: 340504.5 | H6: 8998.12 | I6: 254498.74 | J6: 380495.43 | K6: 1694791
A7: (2017-18) | B7: 203261.4 | C7: 571201.87 | D7: 129029.92 | E7: 62611.59 | F7: 176688.44 | G7: 408091.43 | H7: 11881.4 | I7: 81228.07 | J7: 258635.93 | K7: 1902630
A8: ( 2018-19) | B8: 457534.01 | C8: 663571.62 | D8: 117812.85 | E8: 95080.71 | F8: 28944.58 | G8: 461487.51 | H8: 11527.5 | I8: 6903.62 | J8: 230992.59 | K8: 2073855
A9: (2019-20) | B9: 494070.6 | C9: 556875.55 | D9: 109282.54 | E9: 95553.09 | F9: 9125.21 | G9: 480348.14 | H9: 12374.23 | I9: 6029.11 | J9: 239452.43 | K9: 2003110.9
A10: (2020-21) | B10: 456333.97 | C10: 457718.97 | D10: 134750.39 | E10: 85191.91 | F10: 7251.43 | G10: 470391.24 | H10: 16926.99 | I10: 1614.84 | J10: 389667.08 | K10: 2019846.8
A11: (2021-22) | B11: 591226.14 | C11: 712037.33 | D11: 199728.3 | E11: 104768.66 | F11: 2119.08 | G11: 673100.48 | H11: 23191.03 | I11: 1011.82 | J11: 390808.07 | K11: 2697990.9
A12: (2022-23) | B12: 718521.75 | C12: 825833.64 | D12: 213372.09 | E12: 125862.41 | F12: 4748.29 | G12: 808221.32 | H12: 25085.37 | I12: 430.77 | J12: 319000.11 | K12: 3041075.8
A13: (2023-24) | B13: 820622.09 | C13: 911055.01 | D13: 233118.97 | E13: 141436.16 | F13: -4850.43 | G13: 1010947.8 | H13: 33777.78 | I13: 424.96 | J13: 305362.18 | K13: 3451894.5
A14: ( RE 2024-25) | B14: 908459 | C14: 980000 | D14: 235000 | E14: 153440 | F14: 0 | G14: 1199300 | H14: 55000 | I14: 100 | J14: 305000 | K14: 3836299
A15: ( BE 2025-26) | B15: 1010890 | C15: 1082000 | D15: 240000 | E15: 167110 | F15: 0 | G15: 1357000 | H15: 78000 | I15: 100 | J15: 317000 | K15: 4252100

Sheet  Defence spending
B1: Column Labels
A2: Year | B2: Defence Services | C2: Air Force | D2: Army | E2: Navy | F2: R&D | G2: Grand Total
A3: (2013-14) | B3: 79125.05 | C3: 20160.27 | D3: 87750.54 | E3: 13472.26 | F3: 5696.32 | G3: 206204.44
A4: (2014-15) | B4: 81886.98 | C4: 22685.3 | D4: 99321.39 | E4: 14352 | F4: 6237.08 | G4: 224482.75
A5: (2015-16) | B5: 79958.32 | C5: 21848.9 | D5: 105994.58 | E5: 15320.81 | F5: 6183.9 | G5: 229306.51
A6: (2016-17) | B6: 86370.92 | C6: 25228.14 | D6: 120374.48 | E6: 17469.27 | F6: 6963.69 | G6: 256406.5
A7: (2017-18) | B7: 90445.24 | C7: 28418.8 | D7: 135362.36 | E7: 19344.87 | F7: 8033.79 | G7: 281605.06
A8: (2018-19) | B8: 95230.59 | C8: 29370.54 | D8: 141829.61 | E8: 21738.88 | F8: 8431.44 | G8: 296601.06
A9: (2019-20) | B9: 111092.43 | C9: 31528.49 | D9: 146821.92 | E9: 23087.69 | F9: 9086.14 | G9: 321616.67
A10: (2020-21) | B10: 134304.92 | C10: 34615.96 | D10: 145181.03 | E10: 24710.34 | F10: 8350.77 | G10: 347163.02
A11: (2021-22) | B11: 137986.97 | C11: 35687.93 | D11: 161728.27 | E11: 24426.52 | F11: 8406.22 | G11: 368235.91
A12: (2022-23) | B12: 142940.01 | C12: 47455.55 | D12: 175666.05 | E12: 31343.6 | F12: 9407.79 | G12: 406813
A13: (2023-24) | B13: 154256.28 | C13: 54742.33 | D13: 197020.12 | E13: 35147.8 | F13: 10427.48 | G13: 451594.01
A14: (RE 2024-25) | B14: 159500 | C14: 51876.77 | D14: 204628.97 | E14: 36557.31 | F14: 11330.01 | G14: 463893.06
A15: (BE 2025-26) | B15: 180000 | C15: 55000 | D15: 212030.78 | E15: 39019.8 | F15: 12193 | G15: 498243.58

Sheet Capital Expenditure breakdown
B3: Column Labels | H3: Row Labels | I3: (2023-24)
B4: Capital Expenditure | E4: Capital Expenditure Total | F4: Grand Total | H4: Economic Services | I4: 534009.12
A5: Year | B5: Economic Services | C5: General Services | D5: Social Services | H5: Capital - Civil Aviation | I5: 741.31
A6: (2013-14) | B6: 213379.83 | C6: 167025.27 | D6: 3386.56 | E6: 383791.66 | F6: 383791.66 | H6: Capital - Energy | I6: 6999.23
A7: (2014-15) | B7: 209263.81 | C7: 171882.24 | D7: 4347.51 | E7: 385493.56 | F7: 385493.56 | H7: Capital - Indian Railways (Commercial) | I7: 242537.91
A8: (2015-16) | B8: 450985.07 | C8: 171420.58 | D8: 4903.24 | E8: 627308.89 | F8: 627308.89 | H8: Capital - Industry & Minerals | I8: 6708.31 | K8: Row Labels | L8: Sum of 2023-24
A9: (2016-17) | B9: 400976.72 | C9: 185553.97 | D9: 4537.33 | E9: 591068.02 | F9: 591068.02 | H9: Capital - Roads & Bridges | I9: 269865.27 | K9: Civil Aviation | L9: 741.31
A10: (2017-18) | B10: 595292.47 | C10: 196798 | D10: 8749.6 | E10: 800840.07 | F10: 800840.07 | H10: Capital - Science, Tech & Environment | I10: 7157.09 | K10: Energy | L10: 6999.23
A11: (2018-19) | B11: 781370.21 | C11: 208151.98 | D11: 9148.85 | E11: 998671.04 | F11: 998671.04 | H11: Grand Total | I11: 534009.12 | K11: Indian Railways (Commercial) | L11: 242537.91
A12: (2019-20) | B12: 708946.87 | C12: 235899.85 | D12: 9492.19 | E12: 954338.91 | F12: 954338.91 | K12: Industry & Minerals | L12: 6708.31
A13: (2020-21) | B13: 532931.15 | C13: 277050.57 | D13: 7109.9 | E13: 817091.62 | F13: 817091.62 | K13: Roads & Bridges | L13: 269865.27
A14: (2021-22) | B14: 1059245.3 | C14: 291763.87 | D14: 9445.11 | E14: 1360454.3 | F14: 1360454.3 | K14: Science, Tech & Environment | L14: 7157.09
A15: (2022-23) | B15: 1208979.9 | C15: 304127.5 | D15: 12166.45 | E15: 1525273.9 | F15: 1525273.9
A16: (2023-24) | B16: 1697221.5 | C16: 331743.93 | D16: 8587.45 | E16: 2037552.9 | F16: 2037552.9
A17: (RE 2024-25) | B17: 1720934.8 | C17: 342091.24 | D17: 11503.31 | E17: 2074529.3 | F17: 2074529.3
A18: (BE 2025-26) | B18: 1899102.4 | C18: 389088.88 | D18: 11186.3 | E18: 2299377.6 | F18: 2299377.6

Sheet debt
B4: Column Labels | M4: Year | N4: Total Public Debt | O4: Total Public Debt Repayment | P4: Net New Debt
B5: Capital Receipts | G5: Capital Receipts Total | H5: Grand Total | M5: 2013-14 | N5: 3994966 | O5: 3511291 | P5: 483675
A6: Year | B6: 182 Days Treasury Bills | C6: 364 Days Treasury Bills | D6: 91 Days Treasury Bills | E6: External Debt | F6: Market Loans | M6: 2014-15 | N6: 4218196 | O6: 3707700 | P6: 510496
A7: (2013-14) | B7: 137520.26 | C7: 136956.26 | D7: 580087.59 | E7: 25416.23 | F7: 563674.67 | G7: 1443655 | H7: 1443655 | M7: 2015-16 | N7: 4316950 | O7: 3737657 | P7: 579293
A8: (2014-15) | B8: 147608.18 | C8: 149200.68 | D8: 670312.98 | E8: 33533.89 | F8: 592000 | G8: 1592655.7 | H8: 1592655.7 | M8: 2016-17 | N8: 6134137 | O8: 5678823 | P8: 455314
A9: (2015-16) | B9: 162188.61 | C9: 154033.2 | D9: 686666.71 | E9: 36053.72 | F9: 585000 | G9: 1623942.2 | H9: 1623942.2 | M9: 2017-18 | N9: 6554002 | O9: 5872605 | P9: 681397
A10: (2016-17) | B10: 174035.07 | C10: 142525.75 | D10: 664567.49 | E10: 44191.49 | F10: 583045 | G10: 1608364.8 | H10: 1608364.8 | M10: 2018-19 | N10: 6758482 | O10: 6064945 | P10: 693537
A11: (2017-18) | B11: 185416.61 | C11: 159685 | D11: 774059.95 | E11: 48516.74 | F11: 588000 | G11: 1755678.3 | H11: 1755678.3 | M11: 2019-20 | N11: 7301387 | O11: 6326549 | P11: 974838
A12: (2018-19) | B12: 258020.06 | C12: 208896 | D12: 660165.24 | E12: 50609.44 | F12: 571000 | G12: 1748690.7 | H12: 1748690.7 | M12: 2020-21 | N12: 8162910 | O12: 6184635 | P12: 1978275
A13: (2019-20) | B13: 321689.3 | C13: 217670 | D13: 639472.68 | E13: 63180.3 | F13: 710000 | G13: 1952012.3 | H13: 1952012.3 | M13: 2021-22 | N13: 8249152 | O13: 6645468 | P13: 1603684
A14: (2020-21) | B14: 488606.87 | C14: 458240 | D14: 743488.03 | E14: 123937.57 | F14: 1260115.7 | G14: 3074388.2 | H14: 3074388.2 | M14: 2022-23 | N14: 8864893 | O14: 7199701 | P14: 1665192
A15: (2021-22) | B15: 465678.81 | C15: 407796.43 | D15: 847904.18 | E15: 86664.57 | F15: 968381.54 | G15: 2776425.5 | H15: 2776425.5 | M15: 2023-24 | N15: 9160050 | O15: 7462493 | P15: 1697557
A16: (2022-23) | B16: 549240.87 | C16: 445283.5 | D16: 715950.53 | E16: 93731.28 | F16: 1421000 | G16: 3225206.2 | H16: 3225206.2 | M16: RE 2024-25 | N16: 9693665 | O16: 8407558 | P16: 1286107
A17: (2023-24) | B17: 571191.61 | C17: 457486.99 | D17: 644427.47 | E17: 120429.2 | F17: 1543000 | G17: 3336535.3 | H17: 3336535.3 | M17: BE 2025-26 | N17: 10566349 | O17: 9038648 | P17: 1527701
A18: (RE 2024-25) | B18: 394007.06 | C18: 360809.92 | D18: 747644.75 | E18: 107711.53 | F18: 1400697.4 | G18: 3010870.7 | H18: 3010870.7
A19: (BE 2025-26) | B19: 484082.34 | C19: 360809.92 | D19: 606191.25 | E19: 111013.36 | F19: 1482000 | G19: 3044096.9 | H19: 3044096.9

Sheet NTR
A2: Category | B2: Revenue Receipts
A4: Row Labels | B4: 2013-14 | C4: 2020-21 | D4: 2025-26
A5: Dividends and Profits | B5: 90434.52 | C5: 96877.75 | D5: 325000
A6: Interest Receipts | B6: 43991.35 | C6: 59528.76 | D6: 90237.98
A7: Economic Services | B7: 226411.08 | C7: 228124.6 | D7: 481884.77
A8: General Services | B8: 28956.11 | C8: 39565.88 | D8: 72257.03
A9: Other Communication Services | B9: 40113.76 | C9: 45500.65 | D9: 82442.84
A10: Postal Receipts | B10: 10730.42 | C10: 10632.31 | D10: 12487.11
A11: Grand Total | B11: 440637.24 | C11: 480229.95 | D11: 1064309.7

Sheet Main Data
A1: Consolidated Fund of India (₹ in Crore)
A2: Category | B2: Year | C2: Amount (₹ Crore) | D2: Sub-Category Label
A3: Total Revenue Receipts | B3: 2013-14 | C3: 1217798.8 | D3: Total Revenue Receipts
A4: Revenue Receipts | B4: 2014-15 | C4: 1328909 | D4: Total Revenue Receipts
A5: Revenue Receipts | B5: 2015-16 | C5: 1436160.2 | D5: Total Revenue Receipts
A6: Revenue Receipts | B6: 2016-17 | C6: 1615988 | D6: Total Revenue Receipts
A7: Revenue Receipts | B7: 2017-18 | C7: 1691143.1 | D7: Total Revenue Receipts
A8: Revenue Receipts | B8: 2018-19 | C8: 1806462.9 | D8: Total Revenue Receipts
A9: Revenue Receipts | B9: 2019-20 | C9: 1948083.5 | D9: Total Revenue Receipts
A10: Revenue Receipts | B10: 2020-21 | C10: 1864513.5 | D10: Total Revenue Receipts
A11: Revenue Receipts | B11: 2021-22 | C11: 2436421.5 | D11: Total Revenue Receipts
A12: Revenue Receipts | B12: 2022-23 | C12: 2713267.2 | D12: Total Revenue Receipts
A13: Revenue Receipts | B13: 2023-24 | C13: 3088174.6 | D13: Total Revenue Receipts
A14: Revenue Receipts | B14: RE 2024-25 | C14: 3485869.3 | D14: Total Revenue Receipts
... A54: Capital Expenditure | B54: BE 2025-26 | C54: 10293122 | D54: Total Capital Expenditure

Sheet Sub Components
A1: SUB-COMPONENTS-Consolidated Fund of India (₹ in Crore)
A2: Statement | B2: Category | C2: Sub-Category | D2: Line Item | E2: 2013-14 | F2: 2014-15 | G2: 2015-16 | H2: 2016-17 | I2: 2017-18 | J2: 2018-19 | K2: 2019-20 | L2: 2020-21 | M2: 2021-22 | N2: 2022-23 | O2: 2023-24 | P2: RE 2024-25 | Q2: BE 2025-26
A3: Revenue Receipts | B3: Revenue Receipts | C3: TOTAL | D3: Total Revenue Receipts | E3: ='[1]revenue receipt'!B120 -> 1217798.8 | F3: ='[1]revenue receipt'!C120 -> 1328909 | G3: ='[1]revenue receipt'!D120 -> 1436160.2 | H3: ='[1]revenue receipt'!E120 -> 1615988 | I3: ='[1]revenue receipt'!F120 -> 1691143.1 | J3: ='[1]revenue receipt'!G120 -> 1806462.9 | K3: ='[1]revenue receipt'!H120 -> 1948083.5 | L3: ='[1]revenue receipt'!I120 -> 1864513.5 | ... Q3: ='[1]revenue receipt'!N120 -> 3835268.5
A4: Revenue Receipts | B4: Revenue Receipts | C4: Tax Revenue | D4: Tax Revenue of the Central Govt | E4: ='[1]revenue receipt'!B32 -> 820765.89 | F4: ='[1]revenue receipt'!C32 -> 907327.3 | G4: ='[1]revenue receipt'!D32 -> 949698.13 | H4: ='[1]revenue receipt'!E32 -> 1107967.7 | I4: ='[1]revenue receipt'!F32 -> 1246178.2 | J4: ='[1]revenue receipt'!G32 -> 1319011.3 | K4: ='[1]revenue receipt'!H32 -> 1359382.3 | L4: ='[1]revenue receipt'!I32 -> 1432107.1 | ... Q4: ='[1]revenue receipt'!N32 -> 2847788.9
A5: Revenue Receipts | B5: Revenue Receipts | C5: Tax Revenue - Gross | D5: Gross Tax Revenue | E5: ='[1]revenue receipt'!B30 -> 1138995.5 | F5: ='[1]revenue receipt'!C30 -> 1245135.8 | G5: ='[1]revenue receipt'!D30 -> 1455891.1 | H5: ='[1]revenue receipt'!E30 -> 1715968 | I5: ='[1]revenue receipt'!F30 -> 1919183.5 | J5: ='[1]revenue receipt'!G30 -> 2080465.4 | K5: ='[1]revenue receipt'!H30 -> 2010059.3 | L5: ='[1]revenue receipt'!I30 -> 2027103.8 | ... Q5: ='[1]revenue receipt'!N30 -> 4270233
A6: Revenue Receipts | B6: Revenue Receipts | C6: Tax Revenue - Gross | D6: States' Share (Devolution) | E6: ='[1]revenue receipt'!B31 -> 318229.58 | F6: ='[1]revenue receipt'!C31 -> 337808.45 | G6: ='[1]revenue receipt'!D31 -> 506192.96 | H6: ='[1]revenue receipt'!E31 -> 608000.31 | I6: ='[1]revenue receipt'!F31 -> 673005.29 | J6: ='[1]revenue receipt'!G31 -> 761454.15 | K6: ='[1]revenue receipt'!H31 -> 650677.05 | L6: ='[1]revenue receipt'!I31 -> 594996.76 | ... Q6: ='[1]revenue receipt'!N31 -> 1422444.1
A7: Revenue Receipts | B7: Revenue Receipts | C7: Tax Revenue - GST | D7: GST (Total) | E7: ='[1]revenue receipt'!B4 -> 0 | F7: ='[1]revenue receipt'!C4 -> 0 | G7: ='[1]revenue receipt'!D4 -> 0 | H7: ='[1]revenue receipt'!E4 -> 0 | I7: ='[1]revenue receipt'!F4 -> 444196.53 | J7: ='[1]revenue receipt'!G4 -> 584337.5 | K7: ='[1]revenue receipt'!H4 -> 601783.88 | L7: ='[1]revenue receipt'!I4 -> 551541.51 | ... Q7: ='[1]revenue receipt'!N4 -> 1183355
A8: Revenue Receipts | B8: Revenue Receipts | C8: Tax Revenue - GST | D8: CGST | E8: ='[1]revenue receipt'!B5 -> 0 | F8: ='[1]revenue receipt'!C5 -> 0 | G8: ='[1]revenue receipt'!D5 -> 0 | H8: ='[1]revenue receipt'!E5 -> 0 | I8: ='[1]revenue receipt'!F5 -> 203261.4 | J8: ='[1]revenue receipt'!G5 -> 457534.01 | K8: ='[1]revenue receipt'!H5 -> 494070.6 | L8: ='[1]revenue receipt'!I5 -> 456333.97 | ... Q8: ='[1]revenue receipt'!N5 -> 1010890
A9: Revenue Receipts | B9: Revenue Receipts | C9: Tax Revenue - GST | D9: IGST | E9: ='[1]revenue receipt'!B7 -> 0 | F9: ='[1]revenue receipt'!C7 -> 0 | G9: ='[1]revenue receipt'!D7 -> 0 | H9: ='[1]revenue receipt'!E7 -> 0 | I9: ='[1]revenue receipt'!F7 -> 176688.44 | J9: ='[1]revenue receipt'!G7 -> 28944.58 | K9: ='[1]revenue receipt'!H7 -> 9125.21 | L9: ='[1]revenue receipt'!I7 -> 7251.43 | ... Q9: ='[1]revenue receipt'!N7 -> 0
A10: Revenue Receipts | B10: Revenue Receipts | C10: Tax Revenue - GST | D10: GST Compensation Cess | E10: ='[1]revenue receipt'!B8 -> 0 | F10: ='[1]revenue receipt'!C8 -> 0 | G10: ='[1]revenue receipt'!D8 -> 0 | H10: ='[1]revenue receipt'!E8 -> 0 | I10: ='[1]revenue receipt'!F8 -> 62611.59 | J10: ='[1]revenue receipt'!G8 -> 95080.71 | K10: ='[1]revenue receipt'!H8 -> 95553.09 | L10: ='[1]revenue receipt'!I8 -> 85191.91 | ... Q10: ='[1]revenue receipt'!N8 -> 167110
A11: Revenue Receipts | B11: Revenue Receipts | C11: Tax Revenue - Income & Expenditure | D11: Taxes on Income & Expenditure (Total) | E11: ='[1]revenue receipt'!B9 -> 632517.3 | F11: ='[1]revenue receipt'!C9 -> 687259.5 | G11: ='[1]revenue receipt'!D9 -> 733515.33 | H11: ='[1]revenue receipt'!E9 -> 840530.12 | I11: ='[1]revenue receipt'!F9 -> 990092.49 | J11: ='[1]revenue receipt'!G9 -> 1125047 | K11: ='[1]revenue receipt'!H9 -> 1037155 | L11: ='[1]revenue receipt'!I9 -> 927935.69 | ... Q11: ='[1]revenue receipt'!N9 -> 2442000
A12: Revenue Receipts | B12: Revenue Receipts | C12: Tax Revenue - Income & Expenditure | D12: Corporation Tax | E12: ='[1]revenue receipt'!B10 -> 394677.85 | F12: ='[1]revenue receipt'!C10 -> 428924.74 | G12: ='[1]revenue receipt'!D10 -> 453228.33 | H12: ='[1]revenue receipt'!E10 -> 484923.86 | I12: ='[1]revenue receipt'!F10 -> 571201.87 | J12: ='[1]revenue receipt'!G10 -> 663571.62 | K12: ='[1]revenue receipt'!H10 -> 556875.55 | L12: ='[1]revenue receipt'!I10 -> 457718.97 | ... Q12: ='[1]revenue receipt'!N10 -> 1082000
A13: Revenue Receipts | B13: Revenue Receipts | C13: Tax Revenue - Income & Expenditure | D13: Income Tax (excl. Corp Tax) | E13: ='[1]revenue receipt'!B11 -> 237817.23 | F13: ='[1]revenue receipt'!C11 -> 258325.65 | G13: ='[1]revenue receipt'!D11 -> 280322.5 | H13: ='[1]revenue receipt'!E11 -> 340504.5 | I13: ='[1]revenue receipt'!F11 -> 408091.43 | J13: ='[1]revenue receipt'!G11 -> 461487.51 | K13: ='[1]revenue receipt'!H11 -> 480348.14 | L13: ='[1]revenue receipt'!I11 -> 470391.24 | ... Q13: ='[1]revenue receipt'!N11 -> 1357000
A14: Revenue Receipts | B14: Revenue Receipts | C14: Tax Revenue - Property & Capital | D14: Taxes on Property & Capital Transactions | E14: ='[1]revenue receipt'!B16 -> 6025.37 | F14: ='[1]revenue receipt'!C16 -> 8484.36 | G14: ='[1]revenue receipt'!D16 -> 8429.38 | H14: ='[1]revenue receipt'!E16 -> 9183.26 | I14: ='[1]revenue receipt'!F16 -> 11944.83 | J14: ='[1]revenue receipt'!G16 -> 11568.36 | K14: ='[1]revenue receipt'!H16 -> 12394.04 | L14: ='[1]revenue receipt'!I16 -> 16938.84 | ... Q14: ='[1]revenue receipt'!N16 -> 78000
A15: Revenue Receipts | B15: Revenue Receipts | C15: Tax Revenue - Property & Capital | D15: Securities Transaction Tax | E15: ='[1]revenue receipt'!B21 -> 5017.5 | F15: ='[1]revenue receipt'!C21 -> 7398.15 | G15: ='[1]revenue receipt'!D21 -> 7350.12 | H15: ='[1]revenue receipt'!E21 -> 8998.12 | I15: ='[1]revenue receipt'!F21 -> 11881.4 | J15: ='[1]revenue receipt'!G21 -> 11527.5 | K15: ='[1]revenue receipt'!H21 -> 12374.23 | L15: ='[1]revenue receipt'!I21 -> 16926.99 | ... Q15: ='[1]revenue receipt'!N21 -> 78000
A16: Revenue Receipts | B16: Revenue Receipts | C16: Tax Revenue - Commodities & Services | D16: Taxes on Commodities & Services (excl GST) | E16: ='[1]revenue receipt'!B22 -> 497322.97 | F16: ='[1]revenue receipt'!C22 -> 546188.14 | G16: ='[1]revenue receipt'!D22 -> 710068.12 | H16: ='[1]revenue receipt'!E22 -> 862109.13 | I16: ='[1]revenue receipt'!F22 -> 469864.1 | J16: ='[1]revenue receipt'!G22 -> 356698.37 | K16: ='[1]revenue receipt'!H22 -> 355926.17 | L16: ='[1]revenue receipt'!I22 -> 528115.66 | ... Q16: ='[1]revenue receipt'!N22 -> 562100
A17: Revenue Receipts | B17: Revenue Receipts | C17: Tax Revenue - Commodities & Services | D17: Customs | E17: ='[1]revenue receipt'!B24 -> 172085.42 | F17: ='[1]revenue receipt'!C24 -> 188016.19 | G17: ='[1]revenue receipt'!D24 -> 210338 | H17: ='[1]revenue receipt'!E24 -> 225370.34 | I17: ='[1]revenue receipt'!F24 -> 129029.92 | J17: ='[1]revenue receipt'!G24 -> 117812.85 | K17: ='[1]revenue receipt'!H24 -> 109282.54 | L17: ='[1]revenue receipt'!I24 -> 134750.39 | ... Q17: ='[1]revenue receipt'!N24 -> 240000
A18: Revenue Receipts | B18: Revenue Receipts | C18: Tax Revenue - Commodities & Services | D18: Union Excise Duties | E18: ='[1]revenue receipt'!B25 -> 169455.14 | F18: ='[1]revenue receipt'!C25 -> 188127.6 | G18: ='[1]revenue receipt'!D25 -> 287148.55 | H18: ='[1]revenue receipt'!E25 -> 380495.43 | I18: ='[1]revenue receipt'!F25 -> 258635.93 | J18: ='[1]revenue receipt'!G25 -> 230992.59 | K18: ='[1]revenue receipt'!H25 -> 239452.43 | L18: ='[1]revenue receipt'!I25 -> 389667.08 | ... Q18: ='[1]revenue receipt'!N25 -> 317000
A19: Revenue Receipts | B19: Revenue Receipts | C19: Tax Revenue - Commodities & Services | D19: Service Tax | E19: ='[1]revenue receipt'!B27 -> 154778.12 | F19: ='[1]revenue receipt'!C27 -> 167969.04 | G19: ='[1]revenue receipt'!D27 -> 211414.25 | H19: ='[1]revenue receipt'!E27 -> 254498.74 | I19: ='[1]revenue receipt'!F27 -> 81228.07 | J19: ='[1]revenue receipt'!G27 -> 6903.62 | K19: ='[1]revenue receipt'!H27 -> 6029.11 | L19: ='[1]revenue receipt'!I27 -> 1614.84 | ... Q19: ='[1]revenue receipt'!N27 -> 100
A20: Revenue Receipts | B20: Revenue Receipts | C20: Non-Tax Revenue | D20: Total Non-Tax Revenue | E20: ='[1]revenue receipt'!B119 -> 397032.9 | F20: ='[1]revenue receipt'!C119 -> 421581.66 | G20: ='[1]revenue receipt'!D119 -> 486462.09 | H20: ='[1]revenue receipt'!E119 -> 508020.25 | I20: ='[1]revenue receipt'!F119 -> 444964.86 | J20: ='[1]revenue receipt'!G119 -> 487451.63 | K20: ='[1]revenue receipt'!H119 -> 588701.25 | L20: ='[1]revenue receipt'!I119 -> 432406.39 | ... Q20: ='[1]revenue receipt'!N119 -> 987479.63
A21: Revenue Receipts | B21: Revenue Receipts | C21: Non-Tax Revenue - Fiscal Services | D21: Fiscal Services | E21: ='[1]revenue receipt'!B35 -> 883.77 | F21: ='[1]revenue receipt'!C35 -> 1393.59 | G21: ='[1]revenue receipt'!D35 -> 630.14 | H21: ='[1]revenue receipt'!E35 -> 764.85 | I21: ='[1]revenue receipt'!F35 -> 460.13 | J21: ='[1]revenue receipt'!G35 -> 743.71 | K21: ='[1]revenue receipt'!H35 -> 1041.06 | L21: ='[1]revenue receipt'!I35 -> 1168.8 | ... Q21: ='[1]revenue receipt'!N35 -> 2318.68
A22: Revenue Receipts | B22: Revenue Receipts | C22: Non-Tax Revenue - Interest & Dividends | D22: Interest Receipts, Dividends & Profits | E22: ='[1]revenue receipt'!B38 -> 134425.87 | F22: ='[1]revenue receipt'!C38 -> 137818.23 | G22: ='[1]revenue receipt'!D38 -> 158405.84 | H22: ='[1]revenue receipt'!E38 -> 166478.07 | I22: ='[1]revenue receipt'!F38 -> 137085.12 | J22: ='[1]revenue receipt'!G38 -> 140564.19 | K22: ='[1]revenue receipt'!H38 -> 243083.32 | L22: ='[1]revenue receipt'!I38 -> 156406.51 | ... Q22: ='[1]revenue receipt'!N38 -> 415237.98
A23: Revenue Receipts | B23: Revenue Receipts | C23: Non-Tax Revenue - Interest & Dividends | D23: Interest Receipts | E23: ='[1]revenue receipt'!B39 -> 43991.35 | F23: ='[1]revenue receipt'!C39 -> 47985.19 | G23: ='[1]revenue receipt'!D39 -> 46278.69 | H23: ='[1]revenue receipt'!E39 -> 43461.52 | I23: ='[1]revenue receipt'!F39 -> 45724.65 | J23: ='[1]revenue receipt'!G39 -> 27143.68 | K23: ='[1]revenue receipt'!H39 -> 56950.78 | L23: ='[1]revenue receipt'!I39 -> 59528.76 | ... Q23: ='[1]revenue receipt'!N39 -> 90237.98
A24: Revenue Receipts | B24: Revenue Receipts | C24: Non-Tax Revenue - Interest & Dividends | D24: Dividends and Profits | E24: ='[1]revenue receipt'!B43 -> 90434.52 | F24: ='[1]revenue receipt'!C43 -> 89833.04 | G24: ='[1]revenue receipt'!D43 -> 112127.15 | H24: ='[1]revenue receipt'!E43 -> 123016.55 | I24: ='[1]revenue receipt'!F43 -> 91360.47 | J24: ='[1]revenue receipt'!G43 -> 113420.51 | K24: ='[1]revenue receipt'!H43 -> 186132.54 | L24: ='[1]revenue receipt'!I43 -> 96877.75 | ... Q24: ='[1]revenue receipt'!N43 -> 325000
A25: Revenue Receipts | B25: Revenue Receipts | C25: Non-Tax Revenue - Other | D25: Other Non-Tax Revenue | E25: ='[1]revenue receipt'!B44 -> 114891.32 | F25: ='[1]revenue receipt'!C44 -> 119752.71 | G25: ='[1]revenue receipt'!D44 -> 325544.88 | H25: ='[1]revenue receipt'!E44 -> 339477.74 | I25: ='[1]revenue receipt'!F44 -> 303837.41 | J25: ='[1]revenue receipt'!G44 -> 345080.54 | K25: ='[1]revenue receipt'!H44 -> 344203.9 | L25: ='[1]revenue receipt'!I44 -> 273079.44 | ... Q25: ='[1]revenue receipt'!N44 -> 568748.44
A26: Revenue Receipts | B26: Revenue Receipts | C26: Non-Tax Revenue - Other | D26: NTR: General Services | E26: ='[1]revenue receipt'!B45 -> 28956.11 | F26: ='[1]revenue receipt'!C45 -> 35319.99 | G26: ='[1]revenue receipt'!D45 -> 35513.32 | H26: ='[1]revenue receipt'!E45 -> 40652.03 | I26: ='[1]revenue receipt'!F45 -> 42065.18 | J26: ='[1]revenue receipt'!G45 -> 47322.8 | K26: ='[1]revenue receipt'!H45 -> 45845.22 | L26: ='[1]revenue receipt'!I45 -> 39565.88 | ... Q26: ='[1]revenue receipt'!N45 -> 72257.03
A27: Revenue Receipts | B27: Revenue Receipts | C27: Non-Tax Revenue - Other | D27: NTR: Social & Community Services | E27: ='[1]revenue receipt'!B61 -> 1263.88 | F27: ='[1]revenue receipt'!C61 -> 1674.87 | G27: ='[1]revenue receipt'!D61 -> 10015.1 | H27: ='[1]revenue receipt'!E61 -> 11928.15 | I27: ='[1]revenue receipt'!F61 -> 3008.13 | J27: ='[1]revenue receipt'!G61 -> 3079.9 | K27: ='[1]revenue receipt'!H61 -> 3404.2 | L27: ='[1]revenue receipt'!I61 -> 3790.65 | ... Q27: ='[1]revenue receipt'!N61 -> 11187.46
A28: Revenue Receipts | B28: Revenue Receipts | C28: Non-Tax Revenue - Other | D28: NTR: Economic Services | E28: ='[1]revenue receipt'!B73 -> 226411.08 | F28: ='[1]revenue receipt'!C73 -> 242412.84 | G28: ='[1]revenue receipt'!D73 -> 278478.19 | H28: ='[1]revenue receipt'!E73 -> 285093.53 | I28: ='[1]revenue receipt'!F73 -> 256874.48 | J28: ='[1]revenue receipt'!G73 -> 292788.31 | K28: ='[1]revenue receipt'!H73 -> 293192.67 | L28: ='[1]revenue receipt'!I73 -> 228124.6 | ... Q28: ='[1]revenue receipt'!N73 -> 481884.77
A29: Revenue Receipts | B29: Revenue Receipts | C29: Non-Tax Revenue - Other | D29: NTR: Postal Receipts | E29: ='[1]revenue receipt'!B105 -> 10730.42 | F29: ='[1]revenue receipt'!C105 -> 11635.98 | G29: ='[1]revenue receipt'!D105 -> 12939.79 | H29: ='[1]revenue receipt'!E105 -> 11511 | I29: ='[1]revenue receipt'!F105 -> 12832.76 | J29: ='[1]revenue receipt'!G105 -> 13195.68 | K29: ='[1]revenue receipt'!H105 -> 13558.2 | L29: ='[1]revenue receipt'!I105 -> 10632.31 | ... Q29: ='[1]revenue receipt'!N105 -> 12487.11
A30: Revenue Receipts | B30: Revenue Receipts | C30: Non-Tax Revenue - Other | D30: NTR: Other Communication Services | E30: ='[1]revenue receipt'!B106 -> 40113.76 | F30: ='[1]revenue receipt'!C106 -> 30624.18 | G30: ='[1]revenue receipt'!D106 -> 56478.61 | H30: ='[1]revenue receipt'!E106 -> 70241.14 | I30: ='[1]revenue receipt'!F106 -> 32065.9 | J30: ='[1]revenue receipt'!G106 -> 40815.73 | K30: ='[1]revenue receipt'!H106 -> 69846.43 | L30: ='[1]revenue receipt'!I106 -> 45500.65 | ... Q30: ='[1]revenue receipt'!N106 -> 82442.84
A31: Revenue Receipts | B31: Revenue Receipts | C31: Grants-in-Aid | D31: Grants-in-Aid & Contributions | E31: ='[1]revenue receipt'!B116 -> 3618.06 | F31: ='[1]revenue receipt'!C116 -> 1599.88 | G31: ='[1]revenue receipt'!D116 -> 1881.23 | H31: ='[1]revenue receipt'!E116 -> 1299.59 | I31: ='[1]revenue receipt'!F116 -> 3582.2 | J31: ='[1]revenue receipt'!G116 -> 1063.19 | K31: ='[1]revenue receipt'!H116 -> 372.97 | L31: ='[1]revenue receipt'!I116 -> 1751.64 | ... Q31: ='[1]revenue receipt'!N116 -> 1174.53
A32: Revenue Expenditure | B32: Revenue Expenditure | C32: TOTAL | D32: Total Revenue Expenditure | E32: ='[1]revenue receipt'!B122 -> 1575096.6 | F32: ='[1]revenue receipt'!C122 -> 1695136.8 | G32: ='[1]revenue receipt'!D122 -> 1779528.8 | H32: ='[1]revenue receipt'!E122 -> 1933018.1 | I32: ='[1]revenue receipt'!F122 -> 2140084.5 | J32: ='[1]revenue receipt'!G122 -> 2261570.8 | K32: ='[1]revenue receipt'!H122 -> 2615319.7 | L32: ='[1]revenue receipt'!I122 -> 3314851.9 | ... Q32: ='[1]revenue receipt'!N122 -> 4359702.4
A33: Revenue Expenditure | B33: Revenue Expenditure | C33: General Services | D33: General Services (Total) | E33: ='[1]revenue disbursements '!B3 -> 678742.7 | F33: ='[1]revenue disbursements '!C3 -> 751667.18 | G33: ='[1]revenue disbursements '!D3 -> 803420.84 | H33: ='[1]revenue disbursements '!E3 -> 924736.15 | I33: ='[1]revenue disbursements '!F3 -> 1008488.6 | J33: ='[1]revenue disbursements '!G3 -> 1100283 | K33: ='[1]revenue disbursements '!H3 -> 1210584.8 | L33: ='[1]revenue disbursements '!I3 -> 1294769.2 | ... Q33: ='[1]revenue disbursements '!N3 -> 2182279.6
A34: Revenue Expenditure | B34: Revenue Expenditure | C34: General Services | D34: Organs of State | E34: ='[1]revenue disbursements '!B4 -> 5044.48 | F34: ='[1]revenue disbursements '!C4 -> 5213.82 | G34: ='[1]revenue disbursements '!D4 -> 7300.44 | H34: ='[1]revenue disbursements '!E4 -> 8664.35 | I34: ='[1]revenue disbursements '!F4 -> 7936.69 | J34: ='[1]revenue disbursements '!G4 -> 8538.68 | K34: ='[1]revenue disbursements '!H4 -> 9295.48 | L34: ='[1]revenue disbursements '!I4 -> 8008.86 | ... Q34: ='[1]revenue disbursements '!N4 -> 12737.04
A35: Revenue Expenditure | B35: Revenue Expenditure | C35: General Services | D35: Tax Collection | E35: ='[1]revenue disbursements '!B11 -> 8464 | F35: ='[1]revenue disbursements '!C11 -> 9593.38 | G35: ='[1]revenue disbursements '!D11 -> 10648.57 | H35: ='[1]revenue disbursements '!E11 -> 13000.46 | I35: ='[1]revenue disbursements '!F11 -> 15361.52 | J35: ='[1]revenue disbursements '!G11 -> 16536.59 | K35: ='[1]revenue disbursements '!H11 -> 16834.72 | L35: ='[1]revenue disbursements '!I11 -> 17019.76 | ... Q35: ='[1]revenue disbursements '!N11 -> 55177.64
A36: Revenue Expenditure | B36: Revenue Expenditure | C36: General Services | D36: Interest Payment & Servicing of Debt | E36: ='[1]revenue disbursements '!B20 -> 395199.59 | F36: ='[1]revenue disbursements '!C20 -> 425098.26 | G36: ='[1]revenue disbursements '!D20 -> 457270.38 | H36: ='[1]revenue disbursements '!E20 -> 504512.46 | I36: ='[1]revenue disbursements '!F20 -> 543707.26 | J36: ='[1]revenue disbursements '!G20 -> 595552.17 | K36: ='[1]revenue disbursements '!H20 -> 655370.53 | L36: ='[1]revenue disbursements '!I20 -> 720983.93 | ... Q36: ='[1]revenue disbursements '!N20 -> 1315838
A37: Revenue Expenditure | B37: Revenue Expenditure | C37: General Services | D37: Interest Payments | E37: ='[1]revenue disbursements '!B22 -> 394512.11 | F37: ='[1]revenue disbursements '!C22 -> 425098.26 | G37: ='[1]revenue disbursements '!D22 -> 457232.16 | H37: ='[1]revenue disbursements '!E22 -> 503919.04 | I37: ='[1]revenue disbursements '!F22 -> 543404.14 | J37: ='[1]revenue disbursements '!G22 -> 595530.24 | K37: ='[1]revenue disbursements '!H22 -> 649879.87 | L37: ='[1]revenue disbursements '!I22 -> 711936.57 | ... Q37: ='[1]revenue disbursements '!N22 -> 1313488
A38: Revenue Expenditure | B38: Revenue Expenditure | C38: General Services | D38: Administrative Services | E38: ='[1]revenue disbursements '!B23 -> 52479.96 | F38: ='[1]revenue disbursements '!C23 -> 58552.91 | G38: ='[1]revenue disbursements '!D23 -> 65051.15 | H38: ='[1]revenue disbursements '!E23 -> 76186.88 | I38: ='[1]revenue disbursements '!F23 -> 85190.03 | J38: ='[1]revenue disbursements '!G23 -> 98577.47 | K38: ='[1]revenue disbursements '!H23 -> 109586.86 | L38: ='[1]revenue disbursements '!I23 -> 105083.76 | ... Q38: ='[1]revenue disbursements '!N23 -> 170552.75
A39: Revenue Expenditure | B39: Revenue Expenditure | C39: General Services | D39: Police | E39: ='[1]revenue disbursements '!B26 -> 42994.76 | F39: ='[1]revenue disbursements '!C26 -> 47943.3 | G39: ='[1]revenue disbursements '!D26 -> 53015.02 | H39: ='[1]revenue disbursements '!E26 -> 62732.88 | I39: ='[1]revenue disbursements '!F26 -> 69472.6 | J39: ='[1]revenue disbursements '!G26 -> 80406.35 | K39: ='[1]revenue disbursements '!H26 -> 89866.55 | L39: ='[1]revenue disbursements '!I26 -> 86793.01 | ... Q39: ='[1]revenue disbursements '!N26 -> 141879.63
A40: Revenue Expenditure | B40: Revenue Expenditure | C40: General Services | D40: Pensions & Misc General Services | E40: ='[1]revenue disbursements '!B34 -> 87551.62 | F40: ='[1]revenue disbursements '!C34 -> 107910.62 | G40: ='[1]revenue disbursements '!D34 -> 111285.34 | H40: ='[1]revenue disbursements '!E34 -> 149236.97 | I40: ='[1]revenue disbursements '!F34 -> 163195.74 | J40: ='[1]revenue disbursements '!G34 -> 176909.73 | K40: ='[1]revenue disbursements '!H34 -> 203877.44 | L40: ='[1]revenue disbursements '!I34 -> 227572.6 | ... Q40: ='[1]revenue disbursements '!N34 -> 308118.68
A41: Revenue Expenditure | B41: Revenue Expenditure | C41: General Services | D41: Pensions & Retirement Benefits | E41: ='[1]revenue disbursements '!B35 -> 74896.19 | F41: ='[1]revenue disbursements '!C35 -> 93610.72 | G41: ='[1]revenue disbursements '!D35 -> 96770.94 | H41: ='[1]revenue disbursements '!E35 -> 131400.85 | I41: ='[1]revenue disbursements '!F35 -> 145745.07 | J41: ='[1]revenue disbursements '!G35 -> 160211.49 | K41: ='[1]revenue disbursements '!H35 -> 183954.61 | L41: ='[1]revenue disbursements '!I35 -> 208473.04 | ... Q41: ='[1]revenue disbursements '!N35 -> 277618.32
A42: Revenue Expenditure | B42: Revenue Expenditure | C42: Defence | D42: Defence Services - Revenue (Total) | E42: ='[1]revenue disbursements '!B37 -> 129890.21 | F42: ='[1]revenue disbursements '!C37 -> 145145.95 | G42: ='[1]revenue disbursements '!D37 -> 151599.47 | H42: ='[1]revenue disbursements '!E37 -> 173025.04 | I42: ='[1]revenue disbursements '!F37 -> 192865.24 | J42: ='[1]revenue disbursements '!G37 -> 203882.56 | K42: ='[1]revenue disbursements '!H37 -> 215297.28 | L42: ='[1]revenue disbursements '!I37 -> 215513.72 | ... Q42: ='[1]revenue disbursements '!N37 -> 318723.58
A43: Revenue Expenditure | B43: Revenue Expenditure | C43: Defence | D43: Defence - Army | E43: ='[1]revenue disbursements '!B38 -> 87750.54 | F43: ='[1]revenue disbursements '!C38 -> 99321.39 | G43: ='[1]revenue disbursements '!D38 -> 105994.58 | H43: ='[1]revenue disbursements '!E38 -> 120374.48 | I43: ='[1]revenue disbursements '!F38 -> 135362.36 | J43: ='[1]revenue disbursements '!G38 -> 141829.61 | K43: ='[1]revenue disbursements '!H38 -> 146821.92 | L43: ='[1]revenue disbursements '!I38 -> 145181.03 | ... Q43: ='[1]revenue disbursements '!N38 -> 212030.78
A44: Revenue Expenditure | B44: Revenue Expenditure | C44: Defence | D44: Defence - Navy | E44: ='[1]revenue disbursements '!B39 -> 13472.26 | F44: ='[1]revenue disbursements '!C39 -> 14352 | G44: ='[1]revenue disbursements '!D39 -> 15320.81 | H44: ='[1]revenue disbursements '!E39 -> 17469.27 | I44: ='[1]revenue disbursements '!F39 -> 19344.87 | J44: ='[1]revenue disbursements '!G39 -> 21738.88 | K44: ='[1]revenue disbursements '!H39 -> 23087.69 | L44: ='[1]revenue disbursements '!I39 -> 24710.34 | ... Q44: ='[1]revenue disbursements '!N39 -> 39019.8
A45: Revenue Expenditure | B45: Revenue Expenditure | C45: Defence | D45: Defence - Air Force | E45: ='[1]revenue disbursements '!B40 -> 20160.27 | F45: ='[1]revenue disbursements '!C40 -> 22685.3 | G45: ='[1]revenue disbursements '!D40 -> 21848.9 | H45: ='[1]revenue disbursements '!E40 -> 25228.14 | I45: ='[1]revenue disbursements '!F40 -> 28418.8 | J45: ='[1]revenue disbursements '!G40 -> 29370.54 | K45: ='[1]revenue disbursements '!H40 -> 31528.49 | L45: ='[1]revenue disbursements '!I40 -> 34615.96 | ... Q45: ='[1]revenue disbursements '!N40 -> 55000
A46: Revenue Expenditure | B46: Revenue Expenditure | C46: Defence | D46: Defence - R&D | E46: ='[1]revenue disbursements '!B42 -> 5696.32 | F46: ='[1]revenue disbursements '!C42 -> 6237.08 | G46: ='[1]revenue disbursements '!D42 -> 6183.9 | H46: ='[1]revenue disbursements '!E42 -> 6963.69 | I46: ='[1]revenue disbursements '!F42 -> 8033.79 | J46: ='[1]revenue disbursements '!G42 -> 8431.44 | K46: ='[1]revenue disbursements '!H42 -> 9086.14 | L46: ='[1]revenue disbursements '!I42 -> 8350.77 | ... Q46: ='[1]revenue disbursements '!N42 -> 12193
A47: Capital Receipts | B47: Capital Receipts | C47: TOTAL | D47: Total Capital Account Receipts | E47: ='[1]capital receipt'!B32 -> 4048883.1 | F47: ='[1]capital receipt'!C32 -> 4282482.8 | G47: ='[1]capital receipt'!D32 -> 4400951.2 | H47: ='[1]capital receipt'!E32 -> 6222850.2 | I47: ='[1]capital receipt'!F32 -> 6724689.2 | J47: ='[1]capital receipt'!G32 -> 6883718.4 | K47: ='[1]capital receipt'!H32 -> 7370383.5 | L47: ='[1]capital receipt'!I32 -> 8230730.1 | ... Q47: ='[1]capital receipt'!N32 -> 10760099
A48: Capital Receipts | B48: Capital Receipts | C48: Public Debt | D48: Total Public Debt | E48: ='[1]capital receipt'!B22 -> 3994966.2 | F48: ='[1]capital receipt'!C22 -> 4218196.3 | G48: ='[1]capital receipt'!D22 -> 4316949.7 | H48: ='[1]capital receipt'!E22 -> 6134136.6 | I48: ='[1]capital receipt'!F22 -> 6554001.6 | J48: ='[1]capital receipt'!G22 -> 6758482.4 | K48: ='[1]capital receipt'!H22 -> 7301387 | L48: ='[1]capital receipt'!I22 -> 8162910 | ... Q48: ='[1]capital receipt'!N22 -> 10566349
A49: Capital Receipts | B49: Capital Receipts | C49: Public Debt - Internal | D49: Internal Debt of Central Govt | E49: ='[1]capital receipt'!B20 -> 3969550 | F49: ='[1]capital receipt'!C20 -> 4184662.4 | G49: ='[1]capital receipt'!D20 -> 4280896 | H49: ='[1]capital receipt'!E20 -> 6089945.1 | I49: ='[1]capital receipt'!F20 -> 6505484.8 | J49: ='[1]capital receipt'!G20 -> 6707873 | K49: ='[1]capital receipt'!H20 -> 7238206.7 | L49: ='[1]capital receipt'!I20 -> 8038972.4 | ... Q49: ='[1]capital receipt'!N20 -> 10455335
A50: Capital Receipts | B50: Capital Receipts | C50: Public Debt - Internal | D50: Market Loans | E50: ='[1]capital receipt'!B7 -> 563674.67 | F50: ='[1]capital receipt'!C7 -> 592000 | G50: ='[1]capital receipt'!D7 -> 585000 | H50: ='[1]capital receipt'!E7 -> 583045 | I50: ='[1]capital receipt'!F7 -> 588000 | J50: ='[1]capital receipt'!G7 -> 571000 | K50: ='[1]capital receipt'!H7 -> 710000 | L50: ='[1]capital receipt'!I7 -> 1260115.7 | ... Q50: ='[1]capital receipt'!N7 -> 1482000
A51: Capital Receipts | B51: Capital Receipts | C51: Public Debt - Internal | D51: 14 Days Treasury Bills | E51: ='[1]capital receipt'!B9 -> 2151859.5 | F51: ='[1]capital receipt'!C9 -> 2216124.5 | G51: ='[1]capital receipt'!D9 -> 2449919 | H51: ='[1]capital receipt'!E9 -> 3216118.4 | I51: ='[1]capital receipt'!F9 -> 3790637.9 | J51: ='[1]capital receipt'!G9 -> 3570681.4 | K51: ='[1]capital receipt'!H9 -> 3355188.4 | L51: ='[1]capital receipt'!I9 -> 3745789.9 | ... Q51: ='[1]capital receipt'!N9 -> 6030452.7
A52: Capital Receipts | B52: Capital Receipts | C52: Public Debt - Internal | D52: 91 Days Treasury Bills | E52: ='[1]capital receipt'!B10 -> 580087.59 | F52: ='[1]capital receipt'!C10 -> 670312.98 | G52: ='[1]capital receipt'!D10 -> 686666.71 | H52: ='[1]capital receipt'!E10 -> 664567.49 | I52: ='[1]capital receipt'!F10 -> 774059.95 | J52: ='[1]capital receipt'!G10 -> 660165.24 | K52: ='[1]capital receipt'!H10 -> 639472.68 | L52: ='[1]capital receipt'!I10 -> 743488.03 | ... Q52: ='[1]capital receipt'!N10 -> 606191.25
A53: Capital Receipts | B53: Capital Receipts | C53: Public Debt - Internal | D53: 182 Days Treasury Bills | E53: ='[1]capital receipt'!B11 -> 137520.26 | F53: ='[1]capital receipt'!C11 -> 147608.18 | G53: ='[1]capital receipt'!D11 -> 162188.61 | H53: ='[1]capital receipt'!E11 -> 174035.07 | I53: ='[1]capital receipt'!F11 -> 185416.61 | J53: ='[1]capital receipt'!G11 -> 258020.06 | K53: ='[1]capital receipt'!H11 -> 321689.3 | L53: ='[1]capital receipt'!I11 -> 488606.87 | ... Q53: ='[1]capital receipt'!N11 -> 484082.34
A54: Capital Receipts | B54: Capital Receipts | C54: Public Debt - Internal | D54: 364 Days Treasury Bills | E54: ='[1]capital receipt'!B12 -> 136956.26 | F54: ='[1]capital receipt'!C12 -> 149200.68 | G54: ='[1]capital receipt'!D12 -> 154033.2 | H54: ='[1]capital receipt'!E12 -> 142525.75 | I54: ='[1]capital receipt'!F12 -> 159685 | J54: ='[1]capital receipt'!G12 -> 208896 | K54: ='[1]capital receipt'!H12 -> 217670 | L54: ='[1]capital receipt'!I12 -> 458240 | ... Q54: ='[1]capital receipt'!N12 -> 360809.92
A55: Capital Receipts | B55: Capital Receipts | C55: Public Debt - External | D55: External Debt | E55: ='[1]capital receipt'!B21 -> 25416.23 | F55: ='[1]capital receipt'!C21 -> 33533.89 | G55: ='[1]capital receipt'!D21 -> 36053.72 | H55: ='[1]capital receipt'!E21 -> 44191.49 | I55: ='[1]capital receipt'!F21 -> 48516.74 | J55: ='[1]capital receipt'!G21 -> 50609.44 | K55: ='[1]capital receipt'!H21 -> 63180.3 | L55: ='[1]capital receipt'!I21 -> 123937.57 | ... Q55: ='[1]capital receipt'!N21 -> 111013.36
A56: Capital Receipts | B56: Capital Receipts | C56: Recoveries of Loans | D56: Total Recoveries of Loans & Advances | E56: ='[1]capital receipt'!B29 -> 24549 | F56: ='[1]capital receipt'!C29 -> 26546.7 | G56: ='[1]capital receipt'!D29 -> 41869.8 | H56: ='[1]capital receipt'!E29 -> 40971.1 | I56: ='[1]capital receipt'!F29 -> 70639.16 | J56: ='[1]capital receipt'!G29 -> 30256.94 | K56: ='[1]capital receipt'!H29 -> 18647.18 | L56: ='[1]capital receipt'!I29 -> 29923.16 | ... Q56: ='[1]capital receipt'!N29 -> 146750.01
A57: Capital Receipts | B57: Capital Receipts | C57: Recoveries of Loans | D57: Recoveries from State Governments | E57: ='[1]capital receipt'!B25 -> 10007.6 | F57: ='[1]capital receipt'!C25 -> 10582.32 | G57: ='[1]capital receipt'!D25 -> 11453.53 | H57: ='[1]capital receipt'!E25 -> 12522.85 | I57: ='[1]capital receipt'!F25 -> 13057.3 | J57: ='[1]capital receipt'!G25 -> 14366.77 | K57: ='[1]capital receipt'!H25 -> 15550.89 | L57: ='[1]capital receipt'!I25 -> 16063.28 | ... Q57: ='[1]capital receipt'!N25 -> 84847.61
A58: Capital Receipts | B58: Capital Receipts | C58: Misc Capital Receipts | D58: Miscellaneous Capital Receipts | E58: ='[1]capital receipt'!B31 -> 29367.89 | F58: ='[1]capital receipt'!C31 -> 37739.85 | G58: ='[1]capital receipt'!D31 -> 42131.69 | H58: ='[1]capital receipt'!E31 -> 47742.55 | I58: ='[1]capital receipt'!F31 -> 100048.45 | J58: ='[1]capital receipt'!G31 -> 94979.05 | K58: ='[1]capital receipt'!H31 -> 50349.29 | L58: ='[1]capital receipt'!I31 -> 37896.96 | ... Q58: ='[1]capital receipt'!N31 -> 47000
A59: Capital Expenditure | B59: Capital Expenditure | C59: TOTAL | D59: Total Capital Expenditure | E59: ='[1]capital disbursements'!B157 -> 3711135.7 | F59: ='[1]capital disbursements'!C157 -> 3921706.2 | G59: ='[1]capital disbursements'!D157 -> 4063795.2 | H59: ='[1]capital disbursements'!E157 -> 5988306.4 | I59: ='[1]capital disbursements'!F157 -> 6279856.8 | J59: ='[1]capital disbursements'!G157 -> 6519135.6 | K59: ='[1]capital disbursements'!H157 -> 6759434.7 | L59: ='[1]capital disbursements'!I157 -> 6777429.7 | ... Q59: ='[1]capital disbursements'!N157 -> 10293122
A60: Capital Expenditure | B60: Capital Expenditure | C60: Outside Revenue Account | D60: Cap Exp Outside Revenue Account | E60: ='[1]capital disbursements'!B87 -> 168844.47 | F60: ='[1]capital disbursements'!C87 -> 172085.06 | G60: ='[1]capital disbursements'!D87 -> 278866.34 | H60: ='[1]capital disbursements'!E87 -> 249471.82 | I60: ='[1]capital disbursements'!F87 -> 325115.99 | J60: ='[1]capital disbursements'!G87 -> 399522.74 | K60: ='[1]capital disbursements'!H87 -> 387744.11 | L60: ='[1]capital disbursements'!I87 -> 342948.78 | ... Q60: ='[1]capital disbursements'!N87 -> 956245.31
A61: Capital Expenditure | B61: Capital Expenditure | C61: General Services | D61: Capital Acct - General Services | E61: ='[1]capital disbursements'!B3 -> 87900.22 | F61: ='[1]capital disbursements'!C3 -> 89995.26 | G61: ='[1]capital disbursements'!D3 -> 91462.26 | H61: ='[1]capital disbursements'!E3 -> 99183.05 | I61: ='[1]capital disbursements'!F3 -> 106352.76 | J61: ='[1]capital disbursements'!G3 -> 112921.39 | K61: ='[1]capital disbursements'!H3 -> 124807.42 | L61: ='[1]capital disbursements'!I3 -> 142745.65 | ... Q61: ='[1]capital disbursements'!N3 -> 209088.88
A62: Capital Expenditure | B62: Capital Expenditure | C62: General Services | D62: Capital - Defence Services | E62: ='[1]capital disbursements'!B12 -> 79125.05 | F62: ='[1]capital disbursements'!C12 -> 81886.98 | G62: ='[1]capital disbursements'!D12 -> 79958.32 | H62: ='[1]capital disbursements'!E12 -> 86370.92 | I62: ='[1]capital disbursements'!F12 -> 90445.24 | J62: ='[1]capital disbursements'!G12 -> 95230.59 | K62: ='[1]capital disbursements'!H12 -> 111092.43 | L62: ='[1]capital disbursements'!I12 -> 134304.92 | ... Q62: ='[1]capital disbursements'!N12 -> 180000
A63: Capital Expenditure | B63: Capital Expenditure | C63: Social Services | D63: Capital Acct - Social Services | E63: ='[1]capital disbursements'!B14 -> 3386.56 | F63: ='[1]capital disbursements'!C14 -> 4347.51 | G63: ='[1]capital disbursements'!D14 -> 4903.24 | H63: ='[1]capital disbursements'!E14 -> 4537.33 | I63: ='[1]capital disbursements'!F14 -> 8749.6 | J63: ='[1]capital disbursements'!G14 -> 9148.85 | K63: ='[1]capital disbursements'!H14 -> 9492.19 | L63: ='[1]capital disbursements'!I14 -> 7109.9 | ... Q63: ='[1]capital disbursements'!N14 -> 11186.3
A64: Capital Expenditure | B64: Capital Expenditure | C64: Economic Services | D64: Capital Acct - Economic Services | E64: ='[1]capital disbursements'!B25 -> 76248.11 | F64: ='[1]capital disbursements'!C25 -> 76302.42 | G64: ='[1]capital disbursements'!D25 -> 180796.24 | H64: ='[1]capital disbursements'!E25 -> 144127.34 | I64: ='[1]capital disbursements'!F25 -> 207697.78 | J64: ='[1]capital disbursements'!G25 -> 275851.86 | K64: ='[1]capital disbursements'!H25 -> 252001.86 | L64: ='[1]capital disbursements'!I25 -> 191145.47 | ... Q64: ='[1]capital disbursements'!N25 -> 731222.48
A65: Capital Expenditure | B65: Capital Expenditure | C65: Economic Services | D65: Capital - Energy | E65: ='[1]capital disbursements'!B44 -> 525.47 | F65: ='[1]capital disbursements'!C44 -> 708.59 | G65: ='[1]capital disbursements'!D44 -> 1944.07 | H65: ='[1]capital disbursements'!E44 -> 4533.65 | I65: ='[1]capital disbursements'!F44 -> 2448.52 | J65: ='[1]capital disbursements'!G44 -> 3817.32 | K65: ='[1]capital disbursements'!H44 -> 1374 | L65: ='[1]capital disbursements'!I44 -> 3019.2 | ... Q65: ='[1]capital disbursements'!N44 -> 10646.24
A66: Capital Expenditure | B66: Capital Expenditure | C66: Economic Services | D66: Capital - Industry & Minerals | E66: ='[1]capital disbursements'!B49 -> 3225.76 | F66: ='[1]capital disbursements'!C49 -> 4011.18 | G66: ='[1]capital disbursements'!D49 -> 3624.24 | H66: ='[1]capital disbursements'!E49 -> 4135.05 | I66: ='[1]capital disbursements'!F49 -> 4298.06 | J66: ='[1]capital disbursements'!G49 -> 8526 | K66: ='[1]capital disbursements'!H49 -> 12113.77 | L66: ='[1]capital disbursements'!I49 -> 5212.24 | ... Q66: ='[1]capital disbursements'!N49 -> 12167.36
A67: Capital Expenditure | B67: Capital Expenditure | C67: Economic Services | D67: Capital - Transport (Total) | E67: ='[1]capital disbursements'!B60 -> 48305.1 | F67: ='[1]capital disbursements'!C60 -> 52768.66 | G67: ='[1]capital disbursements'!D60 -> 68249.62 | H67: ='[1]capital disbursements'!E60 -> 92084.8 | I67: ='[1]capital disbursements'!F60 -> 99016.57 | J67: ='[1]capital disbursements'!G60 -> 126787.65 | K67: ='[1]capital disbursements'!H60 -> 138894.7 | L67: ='[1]capital disbursements'!I60 -> 122449.35 | ... Q67: ='[1]capital disbursements'!N60 -> 512582.76
A68: Capital Expenditure | B68: Capital Expenditure | C68: Economic Services | D68: Capital - Indian Railways (Commercial) | E68: ='[1]capital disbursements'!B61 -> 26124.52 | F68: ='[1]capital disbursements'!C61 -> 29199.79 | G68: ='[1]capital disbursements'!D61 -> 35007.87 | H68: ='[1]capital disbursements'!E61 -> 45231.63 | I68: ='[1]capital disbursements'!F61 -> 43285.27 | J68: ='[1]capital disbursements'!G61 -> 52102.61 | K68: ='[1]capital disbursements'!H61 -> 67839.86 | L68: ='[1]capital disbursements'!I61 -> 29909.58 | ... Q68: ='[1]capital disbursements'!N61 -> 251950.81
A69: Capital Expenditure | B69: Capital Expenditure | C69: Economic Services | D69: Capital - Civil Aviation | E69: ='[1]capital disbursements'!B65 -> 6054.63 | F69: ='[1]capital disbursements'!C65 -> 5814.94 | G69: ='[1]capital disbursements'!D65 -> 3361.02 | H69: ='[1]capital disbursements'!E65 -> 2709.27 | I69: ='[1]capital disbursements'!F65 -> 1836.84 | J69: ='[1]capital disbursements'!G65 -> 3975.87 | K69: ='[1]capital disbursements'!H65 -> 21.36 | L69: ='[1]capital disbursements'!I65 -> 35.9 | ... Q69: ='[1]capital disbursements'!N65 -> 45
A70: Capital Expenditure | B70: Capital Expenditure | C70: Economic Services | D70: Capital - Roads & Bridges | E70: ='[1]capital disbursements'!B66 -> 14890.65 | F70: ='[1]capital disbursements'!C66 -> 16572.39 | G70: ='[1]capital disbursements'!D66 -> 29636.4 | H70: ='[1]capital disbursements'!E66 -> 43774.48 | I70: ='[1]capital disbursements'!F66 -> 53524.63 | J70: ='[1]capital disbursements'!G66 -> 69760.86 | K70: ='[1]capital disbursements'!H66 -> 70713.65 | L70: ='[1]capital disbursements'!I66 -> 92293.6 | ... Q70: ='[1]capital disbursements'!N66 -> 259117.56
A71: Capital Expenditure | B71: Capital Expenditure | C71: Economic Services | D71: Capital - Science, Tech & Environment | E71: ='[1]capital disbursements'!B74 -> 3078.35 | F71: ='[1]capital disbursements'!C74 -> 3186.36 | G71: ='[1]capital disbursements'!D74 -> 4036.82 | H71: ='[1]capital disbursements'!E74 -> 5228.65 | I71: ='[1]capital disbursements'!F74 -> 5373.08 | J71: ='[1]capital disbursements'!G74 -> 7294.96 | K71: ='[1]capital disbursements'!H74 -> 9221.6 | L71: ='[1]capital disbursements'!I74 -> 6029.43 | ... Q71: ='[1]capital disbursements'!N74 -> 8123.9
A72: Capital Expenditure | B72: Capital Expenditure | C72: Economic Services | D72: Capital - General Economic Services | E72: ='[1]capital disbursements'!B79 -> 18827.24 | F72: ='[1]capital disbursements'!C79 -> 13609.48 | G72: ='[1]capital disbursements'!D79 -> 98628.75 | H72: ='[1]capital disbursements'!E79 -> 32729.67 | I72: ='[1]capital disbursements'!F79 -> 87636.37 | J72: ='[1]capital disbursements'!G79 -> 123786.79 | K72: ='[1]capital disbursements'!H79 -> 81044.79 | L72: ='[1]capital disbursements'!I79 -> 46793.66 | ... Q72: ='[1]capital disbursements'!N79 -> 108746.25
A73: Capital Expenditure | B73: Capital Expenditure | C73: Economic Services | D73: Investments in Financial Institutions | E73: ='[1]capital disbursements'!B83 -> 16100 | F73: ='[1]capital disbursements'!C83 -> 7090 | G73: ='[1]capital disbursements'!D83 -> 25700.04 | H73: ='[1]capital disbursements'!E83 -> 26422.18 | I73: ='[1]capital disbursements'!F83 -> 90175.35 | J73: ='[1]capital disbursements'!G83 -> 109466.29 | K73: ='[1]capital disbursements'!H83 -> 75721.28 | L73: ='[1]capital disbursements'!I83 -> 36042.72 | ... Q73: ='[1]capital disbursements'!N83 -> 4500.02
A74: Capital Expenditure | B74: Capital Expenditure | C74: Public Debt Repayment | D74: Total Public Debt Repayment | E74: ='[1]capital disbursements'!B108 -> 3511291.3 | F74: ='[1]capital disbursements'!C108 -> 3707699.6 | G74: ='[1]capital disbursements'!D108 -> 3737657 | H74: ='[1]capital disbursements'!E108 -> 5678823.2 | I74: ='[1]capital disbursements'!F108 -> 5872604.6 | J74: ='[1]capital disbursements'!G108 -> 6064945.4 | K74: ='[1]capital disbursements'!H108 -> 6326548.8 | L74: ='[1]capital disbursements'!I108 -> 6184635.3 | ... Q74: ='[1]capital disbursements'!N108 -> 9038648.2
A75: Capital Expenditure | B75: Capital Expenditure | C75: Loans & Advances | D75: Total Loans & Advances | E75: ='[1]capital disbursements'!B156 -> 30999.92 | F75: ='[1]capital disbursements'!C156 -> 41921.53 | G75: ='[1]capital disbursements'!D156 -> 47271.94 | H75: ='[1]capital disbursements'!E156 -> 60011.39 | I75: ='[1]capital disbursements'!F156 -> 82136.18 | J75: ='[1]capital disbursements'!G156 -> 54667.46 | K75: ='[1]capital disbursements'!H156 -> 45141.77 | L75: ='[1]capital disbursements'!I156 -> 249845.55 | ... Q75: ='[1]capital disbursements'!N156 -> 298229.02
A76: Capital Expenditure | B76: Capital Expenditure | C76: Loans & Advances | D76: Loans to State Governments | E76: ='[1]capital disbursements'!B148 -> 11008.1 | F76: ='[1]capital disbursements'!C148 -> 11939.76 | G76: ='[1]capital disbursements'!D148 -> 12504.1 | H76: ='[1]capital disbursements'!E148 -> 17768.59 | I76: ='[1]capital disbursements'!F148 -> 17516.17 | J76: ='[1]capital disbursements'!G148 -> 23828.76 | K76: ='[1]capital disbursements'!H148 -> 24681.05 | L76: ='[1]capital disbursements'!I148 -> 148803.93 | ... Q76: ='[1]capital disbursements'!N148 -> 192833

Sheet revenue receipts
A1: STATEMENT I - CONSOLIDATED FUND OF INDIA - REVENUE ACCOUNT - RECEIPTS
A2: Categories | B2: Actuals 2013-2014 | C2: Actuals 2014-2015 | D2: Actuals 2015-2016 | E2: Actuals 2016-2017 | F2: Actuals 2017-2018 | G2: Actuals 2018-2019 | H2: Actuals 2019-2020 | I2: Actuals 2020-2021 | J2: Actuals 2021-2022 | K2: Actuals 2022-2023 | L2: Actuals 2023-2024 | M2: Revised Estimates 2024-2025 | N2: Budget Estimates 2025-2026
A3: A. TAX REVENUE
A4: (a) Goods and Services Tax | B4: 0 | C4: 0 | D4: 0 | E4: 0 | F4: =SUM(F5:F8) -> 444196.53 | G4: =SUM(G5:G8) -> 584337.5 | H4: =SUM(H5:H8) -> 601783.88 | I4: 551541.51 | J4: 702412.82 | K4: 853900.57 | L4: 962704.98 | M4: 1066839 | N4: 1183355
A5: Central Goods and Services Tax (CGST) | B5: 0 | C5: 0 | D5: 0 | E5: 0 | F5: 203261.4 | G5: 457534.01 | H5: 494070.6 | I5: 456333.97 | J5: 591226.14 | K5: 718521.75 | L5: 820622.09 | M5: 908459 | N5: 1010890
A6: Union Territory Goods and Services Tax (UTGST) | B6: 0 | C6: 0 | D6: 0 | E6: 0 | F6: 1635.1 | G6: 2778.2 | H6: 3034.98 | I6: 2764.2 | J6: 4298.94 | K6: 4768.12 | L6: 5497.16 | M6: 4940 | N6: 5355
A7: Integrated Goods and Services Tax (IGST) | B7: 0 | C7: 0 | D7: 0 | E7: 0 | F7: 176688.44 | G7: 28944.58 | H7: 9125.21 | I7: 7251.43 | J7: 2119.08 | K7: 4748.29 | L7: -4850.43 | M7: 0 | N7: 0
A8: Goods and Services Tax Compensation Cess | B8: 0 | C8: 0 | D8: 0 | E8: 0 | F8: 62611.59 | G8: 95080.71 | H8: 95553.09 | I8: 85191.91 | J8: 104768.66 | K8: 125862.41 | L8: 141436.16 | M8: 153440 | N8: 167110
A9: (b) Taxes on Income and Expenditure | B9: 632517.3 | C9: 687259.5 | D9: 733515.33 | E9: 840530.12 | F9: 990092.49 | G9: 1125047 | H9: 1037155 | I9: 927935.69 | J9: 1385089.5 | K9: 1634008 | L9: 1922033.5 | M9: 2182000 | N9: 2442000
A10: Corporation Tax | B10: 394677.85 | C10: 428924.74 | D10: 453228.33 | E10: 484923.86 | F10: 571201.87 | G10: 663571.62 | H10: 556875.55 | I10: 457718.97 | J10: 712037.33 | K10: 825833.64 | L10: 911055.01 | M10: 980000 | N10: 1082000
A11: Taxes on Income Other Than Corporation Tax | B11: 237817.23 | C11: 258325.65 | D11: 280322.5 | E11: 340504.5 | F11: 408091.43 | G11: 461487.51 | H11: 480348.14 | I11: 470391.24 | J11: 673100.48 | K11: 808221.32 | L11: 1010947.8 | M11: 1199300 | N11: 1357000
A12: Hotel Receipts Tax | B12: 0.61 | C12: 0.94 | D12: 0.59 | E12: 0.48 | F12: 0.5 | G12: 0.44 | H12: 1.26 | I12: 0.3 | J12: 0.25 | K12: 0.66 | L12: 0.34 | M12: 0 | N12: 0
A13: Interest Tax | B13: 8 | C13: 5.58 | D13: 5.31 | E13: 4.98 | F13: 4.45 | G13: 3.19 | H13: 2.09 | I13: 2.36 | J13: 3.96 | K13: 8.46 | L13: 19.93 | M13: 0 | N13: 0
A14: Fringe Benefit Tax | B14: 4.71 | C14: -8.27 | D14: -45.82 | E14: -66.89 | F14: -93.29 | G14: -31.59 | H14: -135.27 | I14: -181.86 | J14: -54.98 | K14: -74.56 | L14: -4.46 | M14: 0 | N14: 0
A15: Other Taxes on Income and Expenditure | B15: 8.9 | C15: 10.86 | D15: 4.42 | E15: 15163.19 | F15: 10887.53 | G15: 15.81 | H15: 63.26 | I15: 4.68 | J15: 2.48 | K15: 18.51 | L15: 14.89 | M15: 2700 | N15: 3000
A16: (c) Taxes on Property and Capital Transactions | B16: =SUM(B18:B21) -> 6025.37 | C16: =SUM(C17:C21) -> 8484.36 | D16: =SUM(D17:D21) -> 8429.38 | E16: =SUM(E17:E21) -> 9183.26 | F16: =SUM(F17:F21) -> 11944.83 | G16: 11568.36 | H16: 12394.04 | I16: 16938.84 | J16: 23203.82 | K16: 25076.35 | L16: 33785.52 | M16: 55000 | N16: 78000
A17: Stamps and Registration Fees | B17: 0 | C17: … | D17: … | E17: 0 | F17: … | G17: … | H17: … | I17: … | J17: 0.46 | K17: 0.2 | L17: 0.31 | M17: 0 | N17: 0
A18: Gift tax | B18: 0.53 | C18: 0.49 | D18: 0 | E18: 0 | F18: 0 | G18: 0 | H18: 0 | I18: 0 | J18: 0 | K18: 0 | N18: 0
A19: Estate Duty | B19: 0.44 | C19: 0.22 | D19: 0.67 | E19: 0.67 | F19: 0.84 | G19: 1.12 | H19: 1.7 | I19: 1.38 | J19: 1.74 | K19: 1.06 | L19: 1.31 | M19: 0 | N19: 0
A20: Taxes on Wealth | B20: 1006.9 | C20: 1085.5 | D20: 1078.59 | E20: 184.47 | F20: 62.59 | G20: 39.74 | H20: 18.11 | I20: 10.47 | J20: 10.59 | K20: -10.28 | L20: 6.12 | M20: 0 | N20: 0
A21: Securities Transaction Tax | B21: 5017.5 | C21: 7398.15 | D21: 7350.12 | E21: 8998.12 | F21: 11881.4 | G21: 11527.5 | H21: 12374.23 | I21: 16926.99 | J21: 23191.03 | K21: 25085.37 | L21: 33777.78 | M21: 55000 | N21: 78000
A22: (d) Taxes on Commodities and Services other than Goods and Services Tax | B22: =SUM(B23:B28) -> 497322.97 | C22: =SUM(C23:C28) -> 546188.14 | D22: =SUM(D23:D28) -> 710068.12 | E22: =SUM(E23:E28) -> 862109.13 | F22: =SUM(F23:F28) -> 469864.1 | G22: =SUM(G23:G28) -> 356698.37 | H22: =SUM(H23:H28) -> 355926.17 | I22: 528115.66 | J22: 595383.93 | K22: 537263.52 | L22: 543249.51 | M22: 545100 | N22: 562100
A23: Banking Cash Transaction Tax | B23: 0.01 | C23: 0 | D23: 0 | E23: 0 | F23: 0.01 | G23: 0 | H23: … | I23: 1.89 | J23: 0.02 | K23: 736.3 | L23: 414.32 | M23: 0 | N23: 0
A24: Customs | B24: 172085.42 | C24: 188016.19 | D24: 210338 | E24: 225370.34 | F24: 129029.92 | G24: 117812.85 | H24: 109282.54 | I24: 134750.39 | J24: 199728.3 | K24: 213372.09 | L24: 233118.97 | M24: 235000 | N24: 240000
A25: Union Excise Duties | B25: 169455.14 | C25: 188127.6 | D25: 287148.55 | E25: 380495.43 | F25: 258635.93 | G25: 230992.59 | H25: 239452.43 | I25: 389667.08 | J25: 390808.07 | K25: 319000.11 | L25: 305362.18 | M25: 305000 | N25: 317000
A26: Sales Tax | B26: 0.75 | C26: 0.85 | D26: ... | E26: 0 | F26: 0 | G26: 0 | H26: ... | I26: ... | J26: 0 | K26: 0 | L26: 0 | M26: 0 | N26: 0
A27: Service Tax | B27: 154778.12 | C27: 167969.04 | D27: 211414.25 | E27: 254498.74 | F27: 81228.07 | G27: 6903.62 | H27: 6029.11 | I27: 1614.84 | J27: 1011.82 | K27: 430.77 | L27: 424.96 | M27: 100 | N27: 100
A28: Other Taxes and Duties on Commodities and Services | B28: 1003.53 | C28: 2074.46 | D28: 1167.32 | E28: 1744.62 | F28: 970.17 | G28: 989.31 | H28: 1162.09 | I28: 2081.46 | J28: 3835.72 | K28: 3724.25 | L28: 3929.08 | M28: 5000 | N28: 5000
A29: (e) Taxes of Union Territories without Legislature | B29: 3129.83 | C29: 3203.75 | D29: 3878.26 | E29: 4145.53 | F29: 3085.58 | G29: 2814.22 | H29: 2800.21 | I29: 2572.14 | J29: 3224.99 | K29: 3943.17 | L29: 3745.09 | M29: 4516.01 | N29: 4778
A30: GROSS TAX REVENUE | B30: 1138995.5 | C30: 1245135.8 | D30: 1455891.1 | E30: 1715968 | F30: 1919183.5 | G30: 2080465.4 | H30: 2010059.3 | I30: 2027103.8 | J30: 2709315.1 | K30: 3054191.6 | L30: 3465518.6 | M30: 3853455 | N30: 4270233
A31: State's share excluded from the Consolidated Fund | B31: 318229.58 | C31: 337808.45 | D31: 506192.96 | E31: 608000.31 | F31: 673005.29 | G31: 761454.15 | H31: 650677.05 | I31: 594996.76 | J31: 898391.57 | K31: 948405.82 | L31: 1129493.7 | M31: 1286885.4 | N31: 1422444.1
A32: Tax Revenue of the Central Government | B32: 820765.89 | C32: 907327.3 | D32: 949698.13 | E32: 1107967.7 | F32: 1246178.2 | G32: 1319011.3 | H32: 1359382.3 | I32: 1432107.1 | J32: 1810923.5 | K32: 2105785.8 | L32: 2336024.9 | M32: 2566569.6 | N32: 2847788.9
A34: B. NON-TAX REVENUE
A35: (a) Fiscal Services | B35: 883.77 | C35: 1393.59 | D35: 630.14 | E35: 764.85 | F35: 460.13 | G35: 743.71 | H35: 1041.06 | I35: 1168.8 | J35: 193.26 | K35: 1127.65 | L35: 1858.12 | M35: 1473.82 | N35: 2318.68
A36: Currency, Coinage and Mint | B36: 740.1 | C36: 1296.72 | D36: 547.2 | E36: 680.32 | F36: 282 | G36: 514.49 | H36: 659.98 | I36: 1093.16 | J36: 103.82 | K36: 443.36 | L36: 178.28 | M36: 133.4 | N36: 212.98
A37: Other Fiscal Services | B37: 143.67 | C37: 96.87 | D37: 82.94 | E37: 84.53 | F37: 178.13 | G37: 229.22 | H37: 381.08 | I37: 75.64 | J37: 89.44 | K37: 684.29 | L37: 1679.84 | M37: 1340.42 | N37: 2105.7
A38: (b) Interest Receipts, Dividends and Profits | B38: 134425.87 | C38: 137818.23 | D38: 158405.84 | E38: 166478.07 | F38: 137085.12 | G38: 140564.19 | H38: 243083.32 | I38: 156406.51 | J38: 206810.28 | K38: 159464.25 | L38: 249528.99 | M38: 372557.09 | N38: 415237.98
A39: Interest Receipts | B39: 43991.35 | C39: 47985.19 | D39: 46278.69 | E39: 43461.52 | F39: 45724.65 | G39: 27143.68 | H39: 56950.78 | I39: 59528.76 | J39: 46163.53 | K39: 59550.41 | L39: 78652.02 | M39: 83272.49 | N39: 90237.98
A40: Interest from State and Union Territory Governments | B40: 8985.11 | C40: 8366.75 | D40: 7858.83 | E40: 7608.36 | F40: 7357.71 | G40: 7402.57 | H40: 7696 | I40: 6316.9 | J40: 6552.18 | K40: 9702.26 | L40: 13641.26 | M40: 14041.86 | N40: 17580.82
A41: Interest from Railways | B41: 7982.94 | C41: 9147.82 | D41: 10144.43 | E41: … | F41: … | G41: … | H41: … | I41: … | J41: … | K41: … | N41: …
A42: Other Interest Receipts | B42: 27023.3 | C42: 30470.62 | D42: 28275.43 | E42: 35853.16 | F42: 38366.94 | G42: 19741.11 | H42: 49254.78 | I42: 53211.86 | J42: 39611.35 | K42: 49848.15 | L42: 65010.76 | M42: 69230.63 | N42: 72657.16
A43: Dividends and Profits | B43: 90434.52 | C43: 89833.04 | D43: 112127.15 | E43: 123016.55 | F43: 91360.47 | G43: 113420.51 | H43: 186132.54 | I43: 96877.75 | J43: 160646.75 | K43: 99913.84 | L43: 170876.97 | M43: 289284.6 | N43: 325000
A44: (c) Other NonTax Revenue | B44: 114891.32 | C44: 119752.71 | D44: 325544.88 | E44: 339477.74 | F44: 303837.41 | G44: 345080.54 | H44: 344203.9 | I44: 273079.44 | J44: 417188.47 | K44: 445002.37 | L44: 499749.92 | M44: 544093.05 | N44: 568748.44
A45: (i) General Services | B45: 28956.11 | C45: 35319.99 | D45: 35513.32 | E45: 40652.03 | F45: 42065.18 | G45: 47322.8 | H45: 45845.22 | I45: 39565.88 | J45: 65742.45 | K45: 56303.68 | L45: 63297.87 | M45: 61367.9 | N45: 72257.03
A46: Public Service Commission | B46: 82.12 | C46: 75.99 | D46: 109.83 | E46: 104.04 | F46: 84.03 | G46: 84.06 | H46: 89.64 | I46: 88.56 | J46: 91.09 | K46: 158.71 | L46: 111.94 | M46: 110.06 | N46: 209.06
A47: Police | B47: 4161.47 | C47: 4806.75 | D47: 5916.01 | E47: 6254.26 | F47: 7495.64 | G47: 8280.72 | H47: 9021.55 | I47: 7290.59 | J47: 27635.5 | K47: 12069.4 | L47: 13190.97 | M47: 12079.44 | N47: 16953.24
A48: Jails | B48: 0 | C48: … | D48: … | E48: … | F48: … | G48: 0.02 | H48: 0.06 | I48: ... | J48: 0 | K48: 0.01 | L48: 0 | M48: 0 | N48: 0
A49: Supplies and Disposals | B49: 156.18 | C49: 152.55 | D49: 153.56 | E49: 228.72 | F49: 54.57 | G49: 0.28 | H49: ... | I49: ... | J49: 5.34 | K49: 0.14 | L49: 0 | M49: 0 | N49: 0
A50: Stationery and Printing | B50: 18.46 | C50: 22.69 | D50: 28.74 | E50: 37.88 | F50: 38.97 | G50: 47.04 | H50: 23.41 | I50: 11.73 | J50: 8 | K50: 26.99 | L50: 9.26 | M50: 11.78 | N50: 11.5
A51: Public Works | B51: 129.53 | C51: 129.48 | D51: 126.67 | E51: 198.74 | F51: 333.85 | G51: 302.47 | H51: 476.9 | I51: 327.99 | J51: 554.16 | K51: 562.62 | L51: 704.07 | M51: 174.29 | N51: 1080.99
A52: Other Administrative Services | B52: 4856.58 | C52: 5462.93 | D52: 5298.36 | E52: 5521.13 | F52: 6203.79 | G52: 6935.86 | H52: 5947.16 | I52: 2518.09 | J52: 4408.86 | K52: 6571.05 | L52: 6787.94 | M52: 5370.66 | N52: 8053.75
A53: Contributions and Recoveries Towards Pension and Other Retirement Benefits | B53: 1272.15 | C53: 1348.13 | D53: 1639.42 | E53: 1703.79 | F53: 1760.7 | G53: 1613.28 | H53: 1335.48 | I53: 1293.79 | J53: 1718.97 | K53: 2719.62 | L53: 2608.86 | M53: 2734.68 | N53: 3929.11
A54: Miscellaneous General Services | B54: 12763.72 | C54: 14982.72 | D54: 16577.77 | E54: 18988.2 | F54: 19355.64 | G54: 21748.08 | H54: 21225.89 | I54: 18309.98 | J54: 24923.6 | K54: 26145.67 | L54: 32589.28 | M54: 33245.93 | N54: 35028.1
A55: Defence Services | B55: 5515.9 | C55: 8338.75 | D55: 5662.96 | E55: 7615.27 | F55: 6737.99 | G55: 8310.99 | H55: 7725.13 | I55: 9725.15 | J55: 6396.93 | K55: 8049.47 | L55: 7295.55 | M55: 7641.06 | N55: 6991.28
A56: Defence Services - Army | B56: 1964.72 | C56: 2540.44 | D56: 2291.32 | E56: 2494.95 | F56: 2951.31 | G56: 3544.51 | H56: 3288 | I56: 4369.45 | J56: 3691.73 | K56: 4634.59 | L56: 4460.93 | M56: 4961.56 | N56: 4510.78
A57: Defence Services - Navy | B57: 437.89 | C57: 673.13 | D57: 328.77 | E57: 332.49 | F57: 629.82 | G57: 882.64 | H57: 700.38 | I57: 1544.29 | J57: 591.53 | K57: 1301.19 | L57: 886.27 | M57: 870 | N57: 870
A58: Defence Services - Air Force | B58: 1066.56 | C58: 2944.24 | D58: 827.95 | E58: 2371.72 | F58: 1025.6 | G58: 1079.29 | H58: 1404.18 | I58: 1790.74 | J58: 1312.48 | K58: 1788.4 | L58: 1717.41 | M58: 1500 | N58: 1300
A59: Defence Services- Coordination & Services (Directorate of Ordnance) | B59: 1977.77 | C59: 1719.32 | D59: 1829.43 | E59: 2062.95 | F59: 1852.02 | G59: 2191.49 | H59: 1928.5 | I59: 1652.56 | J59: 422.52 | K59: 5.55 | L59: 7.14 | M59: 9.5 | N59: 10.5
A60: Defence Services - Research and Development | B60: 68.96 | C60: 461.62 | D60: 385.49 | E60: 353.16 | F60: 279.24 | G60: 613.06 | H60: 404.07 | I60: 368.11 | J60: 378.67 | K60: 319.74 | L60: 223.8 | M60: 300 | N60: 300
A61: (ii) Social and Community Services | B61: 1263.88 | C61: 1674.87 | D61: 10015.1 | E61: 11928.15 | F61: 3008.13 | G61: 3079.9 | H61: 3404.2 | I61: 3790.65 | J61: 4761.09 | K61: 6887.94 | L61: 7669.8 | M61: 6426.34 | N61: 11187.46
... A64: Family Welfare | B64: 23.17 | C64: 33.02 | D64: 18.12 | E64: 17.34 | F64: 14.43 | G64: 12.89 | H64: 34.92 | I64: 6.46 | J64: 0.99 | K64: 27.17 | L64: 36.19 | M64: 19.42 | N64: 19.42
A65: Water Supply and Sanitation | B65: … | C65: ... | D65: ... | E65: ... | F65: ... | G65: ... | H65: ... | I65: ... | J65: 0 | K65: 0 | L65: 601.94 | M65: 656.62 | N65: 1243.15
A66: Housing | B66: 170.8 | C66: 150.49 | D66: 210.98 | E66: 168.7 | F66: 379.28 | G66: 235.58 | H66: 329.73 | I66: 217.64 | J66: 486.28 | K66: 635.38 | L66: 531.43 | M66: 649.89 | N66: 869.3
A67: Urban Development | B67: ... | C67: ... | D67: ... | E67: 0.02 | F67: 0 | G67: 0 | H67: ... | I67: ... | J67: 0 | K67: 0.01 | L67: 0.59 | M67: 0 | N67: 0
A68: Information and Publicity | B68: 612.27 | C68: 209.05 | D68: 2552.39 | E68: 67.3 | F68: 70.79 | G68: 57.53 | H68: 53.23 | I68: 138.25 | J68: 35.3 | K68: 67.33 | L68: 37.77 | M68: 31.77 | N68: 47.9
A69: Broadcasting | B69: ... | C69: 836.52 | D69: 6753 | E69: 1710.3 | F69: 1548.29 | G69: 1319.8 | H69: 912.63 | I69: 1788.52 | J69: 1761.25 | K69: 1123.18 | L69: 972.93 | M69: 814.53 | N69: 1227.9
A70: Labour and Employment | B70: 18.37 | C70: 14.84 | D70: 38.72 | E70: 24.96 | F70: 34.89 | G70: 33.67 | H70: 508.07 | I70: 43.08 | J70: 85.12 | K70: 71.55 | L70: 115.51 | M70: 88.09 | N70: 207.77
A71: Social Security and Welfare | B71: 0.39 | C71: 0.78 | D71: 0.6 | E71: 3427.74 | F71: 0.67 | G71: 1.87 | H71: 2.25 | I71: 0.55 | J71: 3.52 | K71: 54.99 | L71: 600 | M71: 493.52 | N71: 778.03
A72: Other Social Services | B72: ... | C72: ... | D72: ... | E72: 5889.16 | F72: 146.06 | G72: 398.72 | H72: 225.68 | I72: 389.12 | J72: 630.78 | K72: 1163.94 | L72: 1089.09 | M72: 995.23 | N72: 1472.15
A73: (iii) Economic Services | B73: 226411.08 | C73: 242412.84 | D73: 278478.19 | E73: 285093.53 | F73: 256874.48 | G73: 292788.31 | H73: 293192.67 | I73: 228124.6 | J73: 344939.98 | K73: 379620.09 | L73: 425716.59 | M73: 473228.53 | N73: 481884.77
A74: Crop Husbandry | B74: 175.4 | C74: 207.89 | D74: 225.43 | E74: 407.03 | F74: 576.8 | G74: 430.03 | H74: 514.33 | I74: 520.78 | J74: 645.7 | K74: 427.03 | L74: 553.75 | M74: 528.4 | N74: 846.91
A75: Animal Husbandry | B75: 50.55 | C75: 19.64 | D75: 16.78 | E75: 18.81 | F75: 20.59 | G75: 33.43 | H75: 24.45 | I75: 31.87 | J75: 50.08 | K75: 57.01 | L75: 102.2 | M75: 59.81 | N75: 163.23
A76: Dairy Development | B76: 323.32 | C76: 393.74 | D76: 425.15 | E76: 418.98 | F76: 435.5 | G76: 359.24 | H76: 356.11 | I76: 378.93 | J76: 336.49 | K76: 303.92 | L76: 170.64 | M76: 206.1 | N76: 246.1
A77: Fisheries | B77: 3.22 | C77: 3.49 | D77: 4.48 | E77: 4.16 | F77: 3.94 | G77: 3.08 | H77: 3.28 | I77: 3.41 | J77: 4.64 | K77: 8.98 | L77: 22.79 | M77: 18.1 | N77: 34.28
A78: Forestry and Wild Life | B78: 24.97 | C78: 15.95 | D78: 24.42 | E78: 16.17 | F78: 204.43 | G78: 33.24 | H78: 46.54 | I78: 53.17 | J78: 75.09 | K78: 139.89 | L78: 65.18 | M78: 80.41 | N78: 90.33
A79: Food,Storage and Warehousing | B79: ... | C79: 3.15 | D79: 2.09 | E79: 10.22 | F79: 1171 | G79: 540.53 | H79: 541.77 | I79: 574.24 | J79: 671.55 | K79: 438.44 | L79: 453.2 | M79: 381.72 | N79: 792.85
A80: Agricultural Research and Education | B80: 1.29 | C80: 0.06 | D80: 0.05 | E80: 0.01 | F80: 0 | G80: 0 | H80: ... | I80: 103.58 | J80: 199.63 | K80: 7.11 | L80: 3.99 | M80: 87.45 | N80: 221.69
A81: Co-Operation | B81: ... | C81: 0 | D81: 0 | E81: 0 | F81: … | G81: … | H81: … | I81: ... | J81: 0 | K81: 0.09 | L81: 22.53 | M81: 7.41 | N81: 14.03
A82: Other Agricultural Programmes | B82: 15.67 | C82: 16.21 | D82: 17.44 | E82: 18.88 | F82: 21.75 | G82: 22.27 | H82: 22.47 | I82: 23.18 | J82: 21.54 | K82: 21.16 | L82: 21.95 | M82: 18.16 | N82: 34.38
A83: Land Reforms | B83: … | C83: ... | D83: ... | E83: ... | F83: ... | G83: ... | H83: ... | I83: … | J83: … | K83: 93.48 | L83: 40.68 | M83: 18.53 | N83: 67.09
A84: Other Rural Development Programmes | B84: … | C84: ... | D84: ... | E84: ... | F84: ... | G84: ... | H84: 11.69 | I84: 10.98 | J84: 7.93 | K84: 83.63 | L84: 35.39 | M84: 28.9 | N84: 63.21
A85: North Eastern Areas | B85: … | C85: ... | D85: ... | E85: 19 | F85: ... | G85: 3.45 | H85: 3.13 | I85: 9.08 | J85: 7.68 | K85: 24.73 | L85: 23.49 | M85: 1.41 | N85: 0.14
A86: Major and Medium Irrigation | B86: 20.52 | C86: 17.43 | D86: 17.35 | E86: 1.09 | F86: 34.44 | G86: 27.48 | H86: 24.2 | I86: 9.5 | J86: 22.11 | K86: 50.96 | L86: 57.52 | M86: 44.47 | N86: 109.19
A87: Minor Irrigation | B87: 0.16 | C87: 0.52 | D87: 1.04 | E87: 5419.18 | F87: 1.77 | G87: 2.97 | H87: 3.39 | I87: 89.6 | J87: 282.49 | K87: 204.56 | L87: 441.17 | M87: 259.39 | N87: 591.09
A88: Power | B88: 3064.62 | C88: 3286.6 | D88: 14287.66 | E88: 10796.93 | F88: 1975.99 | G88: 3651.31 | H88: 2350.86 | I88: 4317.89 | J88: 7651.44 | K88: 6114.87 | L88: 3782.11 | M88: 5213.78 | N88: 5798.75
A89: Petroleum | B89: 16524.64 | C89: 14480.07 | D89: 9491.98 | E89: 432.73 | F89: 10878.8 | G89: 14197.38 | H89: 11841.14 | I89: 6662.2 | J89: 20036.64 | K89: 19785.02 | L89: 17352.35 | M89: 14277.33 | N89: 21195.43
A90: Coal and Lignite | B90: 136.19 | C90: 6179.26 | D90: 545.09 | E90: 0 | F90: 4.45 | G90: 104.38 | H90: -2.65 | I90: 14.53 | J90: 0.25 | K90: 2.14 | L90: 46.26 | M90: 37.8 | N90: 71.56
A91: Non-Conventional Sources of Energy | B91: 0.9 | C91: 0.14 | D91: ... | E91: 28.1 | F91: 48.23 | G91: 0.04 | H91: 0.04 | I91: 0.01 | J91: 0.15 | K91: 2.57 | L91: 16.57 | M91: 28.2 | N91: 53.39
A92: Village and Small Industries | B92: 29.09 | C92: 23.96 | D92: 19.26 | E92: 3046.12 | F92: 45.33 | G92: 89.91 | H92: 33.51 | I92: 43.4 | J92: 30.38 | K92: 120.47 | L92: 100.7 | M92: 54.9 | N92: 118.69
A93: Industries | B93: 1758.9 | C93: 2024.63 | D93: 1639.31 | E93: 16.12 | F93: 1861.48 | G93: 2068.71 | H93: 1948.5 | I93: 1951.67 | J93: 3459.29 | K93: 3044.16 | L93: 3686.41 | M93: 3507.52 | N93: 4436.62
A94: Non-Ferrous Mining and Metallurgical Industries | B94: 20.56 | C94: 18.21 | D94: 26.82 | E94: 219.19 | F94: 1215.93 | G94: 287.55 | H94: 707.98 | I94: 641.24 | J94: 924.85 | K94: 927.01 | L94: 1010.47 | M94: 928.51 | N94: 1363.87
A95: Other Industries | B95: 347.55 | C95: 255.94 | D95: 231.21 | E95: 90.28 | F95: 182.65 | G95: 155.69 | H95: 195.27 | I95: 164.95 | J95: 204 | K95: 284.5 | L95: 226.31 | M95: 287.58 | N95: 326.8
A96: Indian Railways - Miscellaneous Receipts | B96: ... | C96: … | D96: 4046.1 | E96: 161582.66 | F96: 204.33 | G96: 600.79 | H96: 338.09 | I96: 213.03 | J96: 160.53 | K96: 194.4 | L96: 820.78 | M96: 400 | N96: 700
A97: Indian Railways - Commercial Lines - Revenue Receipts | B97: ... | C97: … | D97: 163497.01 | E97: 3709.54 | F97: 176718.83 | G97: 187738.49 | H97: 172258.5 | I97: 138264.02 | J97: 188687.76 | K97: 237295.81 | L97: 252540.84 | M97: 276714 | N97: 299245
A98: Indian Railways - Strategic Lines - Revenue Receipts | B98: ... | C98: … | D98: 836.5 | E98: 364.64 | F98: 2006.48 | G98: 2168.08 | H98: 2098.1 | I98: 2306.5 | J98: 2518.72 | K98: 2686.75 | L98: 2731.79 | M98: 1886 | N98: 2155
A99: Ports and Light Houses | B99: 225.03 | C99: 255.94 | D99: 281.86 | E99: 140.35 | F99: 325.86 | G99: 307.14 | H99: 330.37 | I99: 384.07 | J99: 371.3 | K99: 401.18 | L99: 441.84 | M99: 488.65 | N99: 513.65
A100: Shipping | B100: 73.09 | C100: 222.28 | D100: 108.18 | E100: 38.66 | F100: 114.62 | G100: 98.41 | H100: 86.36 | I100: 112.38 | J100: 86.71 | K100: 98.31 | L100: 107.92 | M100: 84.6 | N100: 160.16
A101: Civil Aviation | B101: 32.05 | C101: 83.69 | D101: 34.56 | E101: 7323.72 | F101: 67.52 | G101: 133.54 | H101: 258.66 | I101: 144.53 | J101: 234.84 | K101: 199.72 | L101: 278.12 | M101: 393.97 | N101: 844.39
A102: Roads and Bridges | B102: 5297.83 | C102: 33.51 | D102: 6887.31 | E102: 0 | F102: 9064.07 | G102: 19866 | H102: 10394.38 | I102: 10478.52 | J102: 14330 | K102: 22469.99 | L102: 28373.88 | M102: 25353.71 | N102: 36600
A103: Road Transport | B103: ... | C103: 6102.87 | D103: ... | E103: 12.48 | F103: ... | G103: ... | H103: ... | I103: ... | J103: 0 | K103: 0 | L103: 7.47 | M103: 9 | N103: 9
...

Sheet revenue disbursements
A1: STATEMENT I - CONSOLIDATED FUND OF INDIA - REVENUE ACCOUNT - DISBURSEMENTS
A2: Categories | B2: Actuals 2013-2014 | C2: Actuals 2014-2015 | D2: Actuals 2015-2016 | E2: Actuals 2016-2017 | F2: Actuals 2017-2018 | G2: Actuals 2018-2019 | H2: Actuals 2019-2020 | I2: Actuals 2020-2021 | J2: Actuals 2021-2022 | K2: Actuals 2022-2023 | L2: Actuals 2023-2024 | M2: Revised Estimates 2024-2025 | N2: Budget Estimates 2025-2026
A3: A. GENERAL SERVICES | B3: 678742.7 | C3: 751667.18 | D3: 803420.84 | E3: 924736.15 | F3: 1008488.6 | G3: 1100283 | H3: 1210584.8 | I3: 1294769.2 | J3: 1478491.1 | K3: 1677865.9 | L3: 1876063.4 | M3: 2042886.1 | N3: 2182279.6
A4: (a)Organs of State | B4: 5044.48 | C4: 5213.82 | D4: 7300.44 | E4: 8664.35 | F4: 7936.69 | G4: 8538.68 | H4: 9295.48 | I4: 8008.86 | J4: 10077.41 | K4: 12280.97 | L4: 13283.76 | M4: 14107.08 | N4: 12737.04
A5: Parliament/State/Union Territory Legislatures | B5: 794.76 | C5: 754.14 | D5: 835.67 | E5: 920.48 | F5: 948.39 | G5: 1085.86 | H5: 1036.14 | I5: 906.3 | J5: 962.52 | K5: 1049.72 | L5: 1082.48 | M5: 1215.35 | N5: 1278.99
A6: President, Vice President/Governor, Administrator of Union Territories | B6: 42.26 | C6: 45.77 | D6: 57.45 | E6: 61.59 | F6: 62.18 | G6: 67.51 | H6: 78.64 | I6: 75.81 | J6: 76.05 | K6: 89.97 | L6: 99.58 | M6: 132.78 | N6: 139.54
A7: Council of Ministers | B7: 369.36 | C7: 438.25 | D7: 668.75 | E7: 601.34 | F7: 604.52 | G7: 862.79 | H7: 884.85 | I7: 1181.01 | J7: 1300.38 | K7: 954.15 | L7: 876.11 | M7: 676.3 | N7: 761.97
A8: Administration of Justice | B8: 395.07 | C8: 395.16 | D8: 621.88 | E8: 856.68 | F8: 963.58 | G8: 908.81 | H8: 876.31 | I8: 853.4 | J8: 862.95 | K8: 891.86 | L8: 1946.21 | M8: 2265.34 | N8: 2617.25
A9: Elections | B9: 711.47 | C9: 580.65 | D9: 1926.26 | E9: 2453.3 | F9: 1322.22 | G9: 1130.18 | H9: 1624.39 | I9: 259.82 | J9: 1852.79 | K9: 3775.42 | L9: 3535.06 | M9: 3732.03 | N9: 1700.88
A10: Audit | B10: 2731.56 | C10: 2999.85 | D10: 3190.43 | E10: 3770.96 | F10: 4035.8 | G10: 4483.53 | H10: 4795.15 | I10: 4732.52 | J10: 5022.72 | K10: 5519.85 | L10: 5744.32 | M10: 6085.28 | N10: 6238.41
A11: (b)Tax Collection | B11: 8464 | C11: 9593.38 | D11: 10648.57 | E11: 13000.46 | F11: 15361.52 | G11: 16536.59 | H11: 16834.72 | I11: 17019.76 | J11: 67395.6 | K11: 45640.91 | L11: 45881.6 | M11: 51775.99 | N11: 55177.64
A12: Collection of Taxes on Income and Expenditure | B12: 3596.27 | C12: 4045.03 | D12: 4573.06 | E12: 5483.64 | F12: 6019.34 | G12: 6991.43 | H12: 6878.02 | I12: 7138.51 | J12: 7393.75 | K12: 8354.75 | L12: 8546.6 | M12: 9103.65 | N12: 9374.88
A13: Collection of Taxes on Wealth, Securities Transaction Tax and Other Taxes | B13: 91.04 | C13: 102.53 | D13: 115.51 | E13: 139.46 | F13: 152.17 | G13: 176.85 | H13: 173.81 | I13: 180.59 | J13: 186.97 | K13: 211.3 | L13: 215.84 | M13: 230.06 | N13: 236.83
A14: Customs | B14: 2142.06 | C14: 2496.06 | D14: 2798.35 | E14: 3321.58 | F14: 3941.02 | G14: 4418.62 | H14: 4634.16 | I14: 4611.14 | J14: 54452.36 | K14: 31104.11 | L14: 31243.36 | M14: 35935.82 | N14: 38695.41
A15: Union Excise Duties | B15: 2634.63 | C15: 2949.76 | D15: 3161.65 | E15: 4055.78 | F15: 5248.99 | G15: 0 | H15: 0 | I15: 0 | J15: 0 | K15: 0
A16: Collection Charges under Central Goods and Services Tax and Integrated Goods and Services Tax | B16: … | C16: … | D16: 0 | E16: 0 | F16: 0 | G16: 4949.69 | H16: 5148.73 | I16: 5089.52 | J16: 5362.52 | K16: 5970.75 | L16: 5875.8 | M16: 6506.46 | N16: 6870.52
A17: (c)Other Fiscal Services | B17: 112.84 | C17: 152.24 | D17: 265.49 | E17: 109.99 | F17: 232.14 | G17: 285.79 | H17: 322.53 | I17: 586.61 | J17: 583.77 | K17: 660.58 | L17: 1162.13 | M17: 1241.49 | N17: 1131.97
A18: Currency, Coinage and Mint | B18: 0.5 | C18: … | D18: … | E18: … | F18: … | G18: … | H18: … | I18: … | J18: … | K18: … | L18: … | M18: … | N18: …
A19: Other Fiscal Services | B19: 112.34 | C19: 152.24 | D19: 265.49 | E19: 109.99 | F19: 232.14 | G19: 285.79 | H19: 322.53 | I19: 586.61 | J19: 583.77 | K19: 660.58 | L19: 1162.13 | M19: 1241.49 | N19: 1131.97
A20: (d)Interest Payment and Servicing of Debt | B20: 395199.59 | C20: 425098.26 | D20: 457270.38 | E20: 504512.46 | F20: 543707.26 | G20: 595552.17 | H20: 655370.53 | I20: 720983.93 | J20: 828252.59 | K20: 958715.21 | L20: 1102650.2 | M20: 1185170.9 | N20: 1315838
A21: Appropriation for Reduction or Avoidance of Debt | B21: 687.48 | C21: ... | D21: 38.22 | E21: 593.42 | F21: 303.12 | G21: 21.93 | H21: 5490.66 | I21: 9047.36 | J21: 5241.31 | K21: 1025.68 | L21: 782.3 | M21: 2660.59 | N21: 2350
A22: Interest Payments | B22: 394512.11 | C22: 425098.26 | D22: 457232.16 | E22: 503919.04 | F22: 543404.14 | G22: 595530.24 | H22: 649879.87 | I22: 711936.57 | J22: 823011.28 | K22: 957689.53 | L22: 1101867.9 | M22: 1182510.3 | N22: 1313488
A23: (e)Administrative Services | B23: 52479.96 | C23: 58552.91 | D23: 65051.15 | E23: 76186.88 | F23: 85190.03 | G23: 98577.47 | H23: 109586.86 | I23: 105083.76 | J23: 118244.14 | K23: 130975.55 | L23: 141804.86 | M23: 164840.58 | N23: 170552.75
A24: Public Service Commission | B24: 269.89 | C24: 313.33 | D24: 356.81 | E24: 354.64 | F24: 589.11 | G24: 423.16 | H24: 620.01 | I24: 665.16 | J24: 741.88 | K24: 897.51 | L24: 1020.99 | M24: 989.1 | N24: 927.27
A25: Secretariat-General Services | B25: 2597.86 | C25: 2887.84 | D25: 3335 | E25: 4066.53 | F25: 4592.66 | G25: 6721.37 | H25: 7141.77 | I25: 7100.07 | J25: 8043.09 | K25: 9805.67 | L25: 10614.95 | M25: 11610.23 | N25: 11382.29
A26: Police | B26: 42994.76 | C26: 47943.3 | D26: 53015.02 | E26: 62732.88 | F26: 69472.6 | G26: 80406.35 | H26: 89866.55 | I26: 86793.01 | J26: 98283.92 | K26: 107186.53 | L26: 115392.83 | M26: 136306.43 | N26: 141879.63
A27: Jails | B27: 0.81 | C27: 0.5 | D27: 0.85 | E27: 1 | F27: 1.7 | G27: 0.55 | H27: 1 | I27: 1 | J27: 1 | K27: 1 | L27: 1.3 | M27: 5 | N27: 5
A28: Supplies and Disposals | B28: 96.91 | C28: 136.95 | D28: 121.99 | E28: 137.73 | F28: 176.41 | G28: 25 | H28: 50 | I28: 23.84 | J28: 0 | K28: … | L28: … | M28: … | N28: …
A29: Stationery and Printing | B29: 63.55 | C29: 90.47 | D29: 65.14 | E29: 113.75 | F29: 98.99 | G29: 81.55 | H29: 80.73 | I29: 63.61 | J29: 46.58 | K29: 70.08 | L29: 75.44 | M29: 85.6 | N29: 100.72
A30: Public Works | B30: 1444.04 | C30: 1565.43 | D30: 1595.26 | E30: 1774.97 | F30: 1921.56 | G30: 1910.5 | H30: 1957.29 | I30: 1948.11 | J30: 2013.49 | K30: 2155.64 | L30: 2087.9 | M30: 2296.19 | N30: 2436.61
A31: External Affairs | B31: 4450.3 | C31: 4970.66 | D31: 5871.09 | E31: 6261.45 | F31: 7605.74 | G31: 8202.14 | H31: 9021.35 | I31: 7751.76 | J31: 8337.8 | K31: 9950.86 | L31: 11586.41 | M31: 12255.58 | N31: 12468.27
A32: Vigilance | B32: ... | C32: 20.84 | D32: 24.21 | E32: 27.68 | F32: 31.03 | G32: 33.98 | H32: 51.51 | I32: 47.07 | J32: 53.17 | K32: 59.36 | L32: 60.22 | M32: 73.82 | N32: 81.63
A33: Other Administrative Services | B33: 561.84 | C33: 623.59 | D33: 665.78 | E33: 716.25 | F33: 700.23 | G33: 772.87 | H33: 796.65 | I33: 690.13 | J33: 723.21 | K33: 848.9 | L33: 964.82 | M33: 1218.63 | N33: 1271.33
A34: (f)Pensions and Miscellaneous General Services | B34: 87551.62 | C34: 107910.62 | D34: 111285.34 | E34: 149236.97 | F34: 163195.74 | G34: 176909.73 | H34: 203877.44 | I34: 227572.6 | J34: 218981.69 | K34: 265359.82 | L34: 273542.41 | M34: 320886.63 | N34: 308118.68
A35: Pensions and other Retirement Benefits | B35: 74896.19 | C35: 93610.72 | D35: 96770.94 | E35: 131400.85 | F35: 145745.07 | G35: 160211.49 | H35: 183954.61 | I35: 208473.04 | J35: 198946.1 | K35: 241599.29 | L35: 238328.29 | M35: 276102.9 | N35: 277618.32
A36: Miscellaneous General Services | B36: 12655.43 | C36: 14299.9 | D36: 14514.4 | E36: 17836.12 | F36: 17450.67 | G36: 16698.24 | H36: 19922.83 | I36: 19099.56 | J36: 20035.59 | K36: 23760.53 | L36: 35214.12 | M36: 44783.73 | N36: 30500.36
A37: (g)Defence Services | B37: 129890.21 | C37: 145145.95 | D37: 151599.47 | E37: 173025.04 | F37: 192865.24 | G37: 203882.56 | H37: 215297.28 | I37: 215513.72 | J37: 234955.86 | K37: 264232.91 | L37: 297738.47 | M37: 304863.41 | N37: 318723.58
A38: Defence Services - Army | B38: 87750.54 | C38: 99321.39 | D38: 105994.58 | E38: 120374.48 | F38: 135362.36 | G38: 141829.61 | H38: 146821.92 | I38: 145181.03 | J38: 161728.27 | K38: 175666.05 | L38: 197020.12 | M38: 204628.97 | N38: 212030.78
A39: Defence Services - Navy | B39: 13472.26 | C39: 14352 | D39: 15320.81 | E39: 17469.27 | F39: 19344.87 | G39: 21738.88 | H39: 23087.69 | I39: 24710.34 | J39: 24426.52 | K39: 31343.6 | L39: 35147.8 | M39: 36557.31 | N39: 39019.8
A40: Defence Services - Air Force | B40: 20160.27 | C40: 22685.3 | D40: 21848.9 | E40: 25228.14 | F40: 28418.8 | G40: 29370.54 | H40: 31528.49 | I40: 34615.96 | J40: 35687.93 | K40: 47455.55 | L40: 54742.33 | M40: 51876.77 | N40: 55000
A41: Defence Services- Coordination & Services (Directorate of Ordnance) | B41: 2810.82 | C41: 2550.18 | D41: 2251.28 | E41: 2989.46 | F41: 1705.42 | G41: 2512.09 | H41: 4773.04 | I41: 2655.62 | J41: 4706.92 | K41: 359.92 | L41: 400.74 | M41: 470.35 | N41: 480
A42: Defence Services - Research and Development | B42: 5696.32 | C42: 6237.08 | D42: 6183.9 | E42: 6963.69 | F42: 8033.79 | G42: 8431.44 | H42: 9086.14 | I42: 8350.77 | J42: 8406.22 | K42: 9407.79 | L42: 10427.48 | M42: 11330.01 | N42: 12193
A44: B. SOCIAL SERVICES | B44: 131471.07 | C44: 56799.96 | D44: 85418.25 | E44: 93716.98 | F44: 97585.83 | G44: 103676.9 | H44: 131597.12 | I44: 166358.59 | J44: 260826.87 | K44: 207992.06 | L44: 246976.6 | M44: 188817.46 | N44: 198580.18
A45: General Education | B45: 55842.94 | C45: 17376.16 | D45: 18659.34 | E45: 20821.25 | F45: 24982.44 | G45: 21635.84 | H45: 27749.65 | I45: 27742.11 | J45: 29226.01 | K45: 33460.32 | L45: 55215.06 | M45: 39031.96 | N45: 40035.24
... A60: Relief on account of Natural Calamities | B60: 5294.65 | C60: 3918.59 | D60: 10115.42 | E60: 12182.5 | F60: 5580.44 | G60: 10943.05 | H60: 19923.7 | I60: 9352.99 | J60: 9183.82 | K60: 9554.31 | L60: 10623.62 | M60: 13493.7 | N60: 13916.2
A61: Other Social Services | B61: 80.36 | C61: 82.37 | D61: 72.98 | E61: 611.83 | F61: 114.31 | G61: 81.99 | H61: 20.79 | I61: ... | J61: -1.91 | K61: 0 | L61: 4995.65 | M61: 0.01 | N61: 0.01
A62: Secretariat-Social Services | B62: 400.71 | C62: 442.89 | D62: 502.92 | E62: 551.94 | F62: 656.92 | G62: 752.09 | H62: 973.08 | I62: 895.16 | J62: 1004.5 | K62: 1131.22 | L62: 1689.23 | M62: 1858.88 | N62: 1971.25
A64: C. ECONOMIC SERVICES | B64: 558551.98 | C64: 542637.16 | D64: 565724.43 | E64: 614201.15 | F64: 642864.17 | G64: 664814.39 | H64: 731344.47 | I64: 1257012.7 | J64: 1091813.1 | K64: 1226502.2 | L64: 1097936.8 | M64: 1244137.7 | N64: 1235614.9
A65: (a)Agriculture and Allied Activities | B65: 158961.69 | C65: 169711.92 | D65: 201982.21 | E65: 164899.68 | F65: 165020.02 | G65: 176677.96 | H65: 235574.65 | I65: 700537.43 | J65: 475926.47 | K65: 468289.97 | L65: 393122.53 | M65: 376903.41 | N65: 371912.35
A66: Crop Husbandry | B66: 51087.65 | C66: 36628.47 | D66: 39406.38 | E66: 27079.28 | F66: 34093.11 | G66: 46178.39 | H66: 92724.92 | I66: 116860.69 | J66: 138143.48 | K66: 160290.39 | L66: 147331.06 | M66: 138980.98 | N66: 124341.08
A67: Soil and Water Conservation | B67: 18.59 | C67: 18.77 | D67: 18.65 | E67: 20.45 | F67: 23.83 | G67: 25.4 | H67: 26.23 | I67: 26.25 | J67: 26.17 | K67: 33.56 | L67: 32.92 | M67: 35.75 | N67: 38.25
A68: Animal Husbandry | B68: 519.99 | C68: 433.07 | D68: 307.95 | E68: 284.61 | F68: 417.93 | G68: 1003.01 | H68: 1339.81 | I68: 1566.91 | J68: 1804.34 | K68: 1692.81 | L68: 1982.01 | M68: 2210.33 | N68: 2287.17
A69: Dairy Development | B69: 829.39 | C69: 718.04 | D69: 862.4 | E69: 1048.82 | F69: 1119.06 | G69: 1247.32 | H69: 986.68 | I69: 587.39 | J69: 754.87 | K69: 695.15 | L69: 729.68 | M69: 639.9 | N69: 912.75
A70: Fisheries | B70: 210.96 | C70: 244.83 | D70: 252.79 | E70: 117.54 | F70: 99.61 | G70: 202.38 | H70: 211.13 | I70: 263.57 | J70: 346.08 | K70: 361.17 | L70: 272.75 | M70: 517.22 | N70: 712.25
A71: Forestry and Wild Life | B71: 643.55 | C71: 424.26 | D71: 394.18 | E71: 403.85 | F71: 1085.23 | G71: 668.17 | H71: 680.19 | I71: 475.45 | J71: 635.41 | K71: 687.7 | L71: 864.21 | M71: 788.96 | N71: 839.97
A72: Plantations | B72: 610.52 | C72: 628.04 | D72: 626.88 | E72: 524.73 | F72: 646.53 | G72: 599.84 | H72: 703.28 | I72: -708.43 | J72: 698.67 | K72: 763.32 | L72: 709.95 | M72: 845.98 | N72: 1119.25
A73: Food Storage and Warehousing | B73: 93349.85 | C73: 118411.36 | D73: 140921.04 | E73: 115290.99 | F73: 106432.99 | G73: 107319.35 | H73: 114668.54 | I73: 555103.57 | J73: 302542.78 | K73: 274439.57 | L73: 213726.24 | M73: 199652.06 | N73: 206424.42
A74: Agricultural Research and Education | B74: 4726.27 | C74: 4835.77 | D74: 5381.05 | E74: 5722.03 | F74: 6936.21 | G74: 7537.61 | H74: 7517.3 | I74: 7547.81 | J74: 8362.05 | K74: 8366.54 | L74: 9763.44 | M74: 9513.56 | N74: 9772.86
... A86: (d)Irrigation and Flood Control | B86: 846.2 | C86: 1217.62 | D86: 1330.77 | E86: 1202.16 | F86: 1935.83 | G86: 2678.54 | H86: 3314.34 | I86: 4314.37 | J86: 10280.84 | K86: 7318.84 | L86: 10371.02 | M86: 6585.91 | N86: 7980.33
A87: Major Irrigation | B87: ... | C87: ... | D87: 400 | E87: 100 | F87: … | G87: … | H87: … | I87: ... | J87: 4634.46 | K87: 624.34 | L87: 3190.73 | M87: 215.2 | N87: 969
A88: Major and Medium Irrigation | B88: 432.59 | C88: 720.57 | D88: 448.83 | E88: 621.94 | F88: 1382.36 | G88: 2165.49 | H88: 2820.81 | I88: 3931.46 | J88: 5191.62 | K88: 6206.4 | L88: 6711.97 | M88: 5934.62 | N88: 6550.15
A89: Minor Irrigation | B89: 212.68 | C89: 274.62 | D89: 229.23 | E89: 250.92 | F89: 287.33 | G89: 304.3 | H89: 309.86 | I89: 292.01 | J89: 333.04 | K89: 383.45 | L89: 366.59 | M89: 405.5 | N89: 423.16
A90: Flood Control and Drainage | B90: 200.93 | C90: 222.43 | D90: 252.71 | E90: 229.3 | F90: 266.14 | G90: 208.75 | H90: 183.67 | I90: 90.9 | J90: 121.72 | K90: 104.65 | L90: 101.73 | M90: 30.59 | N90: 38.02
A91: (e)Energy | B91: 95257.62 | C91: 73739.04 | D91: 41056.06 | E91: 46352.47 | F91: 46711.64 | G91: 47886.41 | H91: 62343.6 | I91: 56647.92 | J91: 32194.5 | K91: 53135.59 | L91: 43968.94 | M91: 54698.71 | N91: 63392.4
A92: Power | B92: 7436.98 | C92: 7915.69 | D92: 10287.72 | E92: 11804.51 | F92: 15723.23 | G92: 17152.06 | H92: 18381.78 | I92: 14412.56 | J92: 22338.66 | K92: 14778.66 | L92: 21830.61 | M92: 22232.72 | N92: 26592.67
A93: Petroleum | B93: 85395.91 | C93: 60284.86 | D93: 30072.3 | E93: 27637.15 | F93: 24915.81 | G93: 25901.08 | H93: 39986.88 | I93: 39252.79 | J93: 5368.58 | K93: 30781.49 | L93: 14137.57 | M93: 16855.01 | N93: 12520.92
A94: Coal and Lignite | B94: 528.83 | C94: 484.01 | D94: 530.6 | E94: 496.35 | F94: 680.35 | G94: 663.64 | H94: 774.12 | I94: 523.44 | J94: 514.6 | K94: 71.32 | L94: 131.66 | M94: 77.94 | N94: 432.04
A95: New and Renewable Energy | B95: 1895.9 | C95: 5054.48 | D95: 165.44 | E95: 6414.46 | F95: 5392.25 | G95: 4169.63 | H95: 3200.82 | I95: 2459.13 | J95: 3972.66 | K95: 7504.12 | L95: 7869.1 | M95: 15533.04 | N95: 23846.77
A96: (f)Industry and Minerals | B96: 40940.41 | C96: 52963.85 | D96: 53173.97 | E96: 74544.88 | F96: 89118.61 | G96: 76055.96 | H96: 81546.2 | I96: 116626.53 | J96: 150284.15 | K96: 213635.34 | L96: 177623.77 | M96: 181345.16 | N96: 181763.18
A97: Village and Small Industries | B97: 4010.29 | C97: 3704.16 | D97: 4349.12 | E97: 5071.5 | F97: 7536.48 | G97: 7679.4 | H97: 8129.25 | I97: 6644.59 | J97: 16228.31 | K97: 24639.41 | L97: 22749.13 | M97: 16656.84 | N97: 21919.53
A98: Industries | B98: 34892.87 | C98: 46937.22 | D98: 46000.01 | E98: 67410.84 | F98: 77602.09 | G98: 62673.41 | H98: 67549.53 | I98: 101721.85 | J98: 124057.7 | K98: 183828.2 | L98: 148622.47 | M98: 158953.51 | N98: 155880.9
A99: Non-Ferrous Mining and Metallurgical Industries | B99: 674.9 | C99: 818.43 | D99: 918.71 | E99: 1013.92 | F99: 1150.22 | G99: 1203.15 | H99: 1276.6 | I99: 1258.11 | J99: 4130.1 | K99: 1485.62 | L99: 2696.94 | M99: 2943.07 | N99: 2809.45
... A103: Indian Railways - Policy Formulation, Direction, Research and Other Miscelllaneous Organisations | B103: 143213.88 | C103: 161017.25 | D103: 1315.2 | E103: 1439.87 | F103: 1429.81 | G103: 1953.2 | H103: 1785.86 | I103: 1668.56 | J103: 1785.26 | K103: 2003.8 | L103: 1940.12 | M103: 2500 | N103: 2700
A104: Indian Railways - Commercial Lines - Working Expenses | D104: 147835.94 | E104: 157979.08 | F104: 173827.74 | G104: 182840.3 | H104: 169221.11 | I104: 135227.28 | J104: 202200.71 | K104: 233023.19 | L104: 248161.82 | M104: 273272.69 | N104: 294203.69
A105: Indian Railways - Strategic Lines - Working Expenses | D105: 8722.51 | E105: 1050.53 | F105: 2006.48 | G105: 1940 | H105: 2098.1 | I105: 1340.23 | J105: 2405.62 | K105: 2632.59 | L105: 2731.8 | M105: 1886 | N105: 2155
A106: Appropriation from Railway Surplus | B106: … | C106: … | D106: 10505.96 | E106: 4913 | F106: 1665.61 | G106: 3773.86 | H106: 1589.62 | I106: 2547.48 | J106: 0 | K106: 2517.38 | L106: 3259.68 | M106: 1341.31 | N106: 3041.31
A107: Ports and Light Houses | B107: 643.09 | C107: 629.33 | D107: 702.36 | E107: 744.7 | F107: 765.04 | G107: 773.26 | H107: 697.59 | I107: 700.35 | J107: 921.84 | K107: 1008.46 | L107: 1062.14 | M107: 1348.21 | N107: 1376.72
A108: Shipping | B108: 70.54 | C108: 91.96 | D108: 176.44 | E108: 148.68 | F108: 127.25 | G108: 124.22 | H108: 89.82 | I108: 116.74 | J108: 132.29 | K108: 189.94 | L108: 213.87 | M108: 308.57 | N108: 273.62
A109: Civil Aviation | B109: 875.63 | C109: 834.51 | D109: 275.81 | E109: 339.86 | F109: 660.13 | G109: 5661.57 | H109: 3675.16 | I109: 4054.93 | J109: 5045.38 | K109: 9286.58 | L109: 2052.12 | M109: 2385.12 | N109: 2119.34
A110: Roads and Bridges | B110: 23840.04 | C110: 21590.83 | D110: 25523.41 | E110: 25142.12 | F110: 18764.57 | G110: 14313.36 | H110: 3120.32 | I110: 4206.28 | J110: 4048.7 | K110: 4044.79 | L110: 16186.46 | M110: 22354.58 | N110: 6307.23
A111: Road Transport | B111: 133.05 | C111: 121.86 | D111: 128.03 | E111: 119.09 | F111: 142.08 | G111: 158.37 | H111: 140.2 | I111: 220.53 | J111: 158.41 | K111: 213.57 | L111: 248.99 | M111: 370.8 | N111: 565.02
A112: Inland Water Transport | B112: 314.18 | C112: 192.26 | D112: 330.72 | E112: 367.79 | F112: 452.95 | G112: 870.64 | H112: 506.39 | I112: 531.12 | J112: 23.5 | K112: 76.33 | L112: 76.5 | M112: 76.5 | N112: 76.5
A113: Other Transport Services | B113: 4070.12 | C113: 4748.33 | D113: 4434.63 | E113: 3594.45 | F113: 1891.38 | G113: 2139.95 | H113: 2153.29 | I113: 2851.83 | J113: 2924.49 | K113: 3149.14 | L113: 3210.4 | M113: 3357.49 | N113: 3462.29
A114: (h)Communications | B114: 18656.68 | C114: 20635.53 | D114: 28710.55 | E114: 34307.74 | F114: 33366.49 | G114: 34206.86 | H114: 37709.84 | I114: 50688.16 | J114: 42520.44 | K114: 79404.27 | L114: 43848.35 | M114: 65543.34 | N114: 46166.03
A115: Postal Services | B115: 16203.52 | C115: 17894.57 | D115: 18946.97 | E115: 23456 | F115: 24874.04 | G115: 27173.07 | H115: 28371.33 | I115: 28327.61 | J115: 29721.43 | K115: 31456.33 | L115: 34389.64 | M115: 36744.48 | N115: 38620.54
A116: Satellite Systems | B116: 150.86 | C116: 182.6 | D116: 239.18 | E116: … | F116: … | G116: … | H116: … | I116: … | J116: … | K116: … | L116: … | M116: … | N116: …
A117: Other Communication Services | B117: 2302.3 | C117: 2558.36 | D117: 9524.4 | E117: 10851.74 | F117: 8492.45 | G117: 7033.79 | H117: 9338.51 | I117: 22360.55 | J117: 12799.01 | K117: 47947.94 | L117: 9458.71 | M117: 28798.86 | N117: 7545.49
A118: (i)Science Technology and Environment | B118: 15462.2 | C118: 16840.69 | D118: 19695.43 | E118: 20882.04 | F118: 24572.78 | G118: 26914.88 | H118: 28094.45 | I118: 24516.31 | J118: 28331.23 | K118: 28755.38 | L118: 29856.08 | M118: 35924.28 | N118: 40926.48
A119: Atomic Energy Research | B119: 4107.76 | C119: 4188.23 | D119: 4891.13 | E119: 5073.79 | F119: 5786.35 | G119: 5715.54 | H119: 6483.57 | I119: 5913.91 | J119: 6111.46 | K119: 7006.76 | L119: 7337.42 | M119: 9226.66 | N119: 9627.94
A120: Space Research | B120: 2556.48 | C120: 3146.65 | D120: 3609.7 | E120: 4377.02 | F120: 5294.6 | G120: 5602.77 | H120: 5785.52 | I120: 4818.76 | J120: 5525.86 | K120: 5772.57 | L120: 6171.14 | M120: 6865.38 | N120: 7198.77
A121: Oceanographic Research | B121: 485.35 | C121: 467.58 | D121: 480.82 | E121: 412.34 | F121: 531.01 | G121: 690.39 | H121: 649.09 | I121: 432.89 | J121: 712.72 | K121: 535.95 | L121: 717.49 | M121: 1273.29 | N121: 1089.4
A122: Other Scientific Research | B122: 7227.9 | C122: 7831.73 | D122: 9243.27 | E122: 10105.05 | F122: 11408.44 | G122: 11795.43 | H122: 12576.11 | I122: 11234.3 | J122: 13049.09 | K122: 12274.61 | L122: 11470.17 | M122: 14142.93 | N122: 18184.09
A123: Ecology and Environment | B123: 1084.71 | C123: 1206.5 | D123: 1470.51 | E123: 913.84 | F123: 1552.38 | G123: 3110.75 | H123: 2600.16 | I123: 2116.45 | J123: 2932.1 | K123: 3165.49 | L123: 4159.86 | M123: 4416.02 | N123: 4826.28
A124: (j)General Economic Services | B124: 12546.97 | C124: 12132.62 | D124: 13223.12 | E124: 22673.58 | F124: 19352.87 | G124: 17752.57 | H124: 19171.42 | I124: 34421.64 | J124: 28862.65 | K124: 20180.4 | L124: 24597.17 | M124: 57093.98 | N124: 35648.07
A125: Secretariat-Economic Services | B125: 2635.47 | C125: 2752.9 | D125: 2905.03 | E125: 3901.7 | F125: 3383.3 | G125: 4233.87 | H125: 4070.25 | I125: 3995.97 | J125: 5027.29 | K125: 4986.13 | L125: 6161.18 | M125: 6694.73 | N125: 17180.79
A126: Tourism | B126: 625.94 | C126: 559.76 | D126: 689.05 | E126: 1623.84 | F126: 1758.97 | G126: 2082.38 | H126: 1354.97 | I126: 1090.19 | J126: 773.96 | K126: 672.68 | L126: 790.89 | M126: 759.7 | N126: 2282.53
A127: Foreign Trade and Export Promotion | B127: 3526.38 | C127: 3747.24 | D127: 3988.37 | E127: 3531.75 | F127: 4449.77 | G127: 4872.57 | H127: 5116.74 | I127: 3290.92 | J127: 5707.32 | K127: 5768.7 | L127: 5137.62 | M127: 4175.26 | N127: 3517.78
A128: Census Surveys and Statistics | B128: 2466.28 | C128: 2300.89 | D128: 2470.29 | E128: 1605.69 | F128: 1399.23 | G128: 1544.71 | H128: 3304.71 | I128: 2548.1 | J128: 2938 | K128: 2763.26 | L128: 2525.09 | M128: 2407.55 | N128: 2523.29
... A138: Technical and Economic Co-operation with Other Countries | B138: 5285.78 | C138: 5069.46 | D138: 5485.78 | E138: 5124.94 | F138: 372742.03 | G138: 368172.37 | H138: 7819.88 | I138: 7745.28 | J138: 565013.36 | K138: 580242.97 | L138: 7455.62 | M138: 10166.01 | N138: 6511.79
A139: Aid Materials and Equipment | B139: ... | C139: ... | D139: ... | E139: 0 | F139: 3759.82 | G139: 7824.92 | H139: … | I139: … | J139: 51127.95 | K139: 71405.23 | L139: 0 | M139: 0 | N139: 0
...

Sheet capital receipts
A1: STATEMENT I - CONSOLIDATED FUND OF INDIA - CAPITAL ACCOUNT - RECEIPT
A2: Categories | B2: Actuals 2013-2014 | C2: Actuals 2014-2015 | D2: Actuals 2015-2016 | E2: Actuals 2016-2017 | F2: Actuals 2017-2018 | G2: Actuals 2018-2019 | H2: Actuals 2019-2020 | I2: Actuals 2020-2021 | J2: Actuals 2021-2022 | K2: Actuals 2022-2023 | L2: Actuals 2023-2024 | M2: Revised Estimates 2024-2025 | N2: Budget Estimates 2025-2026
A3: A. PUBLIC DEBT
A4: Internal Debt of Central Government
A5: Market Stabilisation Scheme | B5: 0 | C5: ... | D5: … | E5: 1011518.5 | F5: 100000 | G5: 0 | H5: 0 | I5: 0 | J5: 0 | K5: 0 | L5: 0 | M5: 0 | N5: 0
A6: Securities against Small Savings | B6: 13659.53 | C6: 33528.31 | D6: 54237.47 | E6: 72439.14 | F6: 108661 | G6: 138533 | H6: 262413.32 | I6: 526234.99 | J6: 638017.49 | K6: 533539.69 | L6: 684136.52 | M6: 752355.9 | N6: 622891.5
A7: Market Loans | B7: 563674.67 | C7: 592000 | D7: 585000 | E7: 583045 | F7: 588000 | G7: 571000 | H7: 710000 | I7: 1260115.7 | J7: 968381.54 | K7: 1421000 | L7: 1543000 | M7: 1400697.4 | N7: 1482000
A8: Switching of Securities | B8: 31472.28 | C8: 37373.75 | D8: 38300.03 | E8: … | F8: 59158.98 | G8: 28591.26 | H8: 164821.53 | I8: 157042.44 | J8: 196894.08 | K8: 103065.72 | L8: 100289.87 | M8: 146793.65 | N8: 250000
A9: 14 Days Treasury Bills | B9: 2151859.5 | C9: 2216124.5 | D9: 2449919 | E9: 3216118.4 | F9: 3790637.9 | G9: 3570681.4 | H9: 3355188.4 | I9: 3745789.9 | J9: 4432508.1 | K9: 4868275.3 | L9: 4838804.6 | M9: 5719741.8 | N9: 6030452.7
A10: 91 Days Treasury Bills | B10: 580087.59 | C10: 670312.98 | D10: 686666.71 | E10: 664567.49 | F10: 774059.95 | G10: 660165.24 | H10: 639472.68 | I10: 743488.03 | J10: 847904.18 | K10: 715950.53 | L10: 644427.47 | M10: 747644.75 | N10: 606191.25
A11: 182 Days Treasury Bills | B11: 137520.26 | C11: 147608.18 | D11: 162188.61 | E11: 174035.07 | F11: 185416.61 | G11: 258020.06 | H11: 321689.3 | I11: 488606.87 | J11: 465678.81 | K11: 549240.87 | L11: 571191.61 | M11: 394007.06 | N11: 484082.34
A12: 364 Days Treasury Bills | B12: 136956.26 | C12: 149200.68 | D12: 154033.2 | E12: 142525.75 | F12: 159685 | G12: 208896 | H12: 217670 | I12: 458240 | J12: 407796.43 | K12: 445283.5 | L12: 457486.99 | M12: 360809.92 | N12: 360809.92
A13: Cash Management Bills | B13: 242425 | C13: 316116 | D13: ... | E13: 0 | F13: 150000 | G13: 190000 | H13: 300000 | I13: 80000 | J13: 0 | K13: 0 | L13: 0 | M13: 0 | N13: 50000
A14: Ways & Means Advances | B14: 107195 | C14: 10000 | D14: 83843 | E14: 163489 | F14: 480042 | G14: 955243 | H14: 1179582 | I14: 398990 | J14: 0 | K14: 106273 | L14: 150636 | M14: 55000 | N14: 500000
A15: Issuance of Special Securities to EXIM Bank | B15: 0 | C15: … | D15: … | E15: … | F15: 0 | G15: 4500 | H15: 550 | I15: 0 | J15: 0 | K15: 0 | L15: 0 | M15: 0 | N15: 0
A16: Borrowing for providing back to back loans to States and UTs for GST compensation cess shortfall | B16: 0 | C16: … | D16: … | E16: … | F16: 0 | G16: … | H16: … | I16: … | J16: 159000 | K16: … | L16: … | M16: … | N16: …
A17: Issuance of Special Securities to Public Sector Banks | B17: 0 | C17: … | D17: … | E17: … | F17: 80000 | G17: 106000 | H17: 65443 | I17: 20000 | J17: 4600 | K17: 0 | L17: 0 | M17: 0 | N17: 0.01
A18: Currency, Coinage and Mint | B18: 0 | C18: … | D18: … | E18: … | F18: … | G18: … | H18: … | I18: … | J18: … | K18: … | L18: … | M18: … | N18: …
A19: Others | B19: 4699.87 | C19: 12398.03 | D19: 66708.01 | E19: 20581.63 | F19: 29823.37 | G19: 16243.02 | H19: 11521.84 | I19: 46256.4 | J19: 41706.41 | K19: 28532.71 | L19: 49647.64 | M19: 8903.47 | N19: 68907.73
A20: Total-Internal Debt of Central Government | B20: 3969550 | C20: 4184662.4 | D20: 4280896 | E20: 6089945.1 | F20: 6505484.8 | G20: 6707873 | H20: 7238206.7 | I20: 8038972.4 | J20: 8162487.1 | K20: 8771161.3 | L20: 9039620.7 | M20: 9585953.9 | N20: 10455335
A21: External Debt | B21: 25416.23 | C21: 33533.89 | D21: 36053.72 | E21: 44191.49 | F21: 48516.74 | G21: 50609.44 | H21: 63180.3 | I21: 123937.57 | J21: 86664.57 | K21: 93731.28 | L21: 120429.2 | M21: 107711.53 | N21: 111013.36
A22: TOTAL - PUBLIC DEBT | B22: 3994966.2 | C22: 4218196.3 | D22: 4316949.7 | E22: 6134136.6 | F22: 6554001.6 | G22: 6758482.4 | H22: 7301387 | I22: 8162910 | J22: 8249151.7 | K22: 8864892.6 | L22: 9160049.9 | M22: 9693665.4 | N22: 10566349
A24: B. RECOVERIES OF LOANS AND ADVANCES
A25: State Governments | B25: 10007.6 | C25: 10582.32 | D25: 11453.53 | E25: 12522.85 | F25: 13057.3 | G25: 14366.77 | H25: 15550.89 | I25: 16063.28 | J25: 17491.18 | K25: 19890.69 | L25: 92856.68 | M25: 135595.97 | N25: 84847.61
A26: Union Territories (With Legislature) | B26: 111.66 | C26: 75.33 | D26: 59.4 | E26: 54.86 | F26: 66.81 | G26: 72 | H26: 72 | I26: 43.71 | J26: 77.49 | K26: 141.57 | L26: 6215 | M26: 8513.21 | N26: 4381.47
A27: Foreign Governments | B27: 344.1 | C27: 722.05 | D27: 416.83 | E27: 396.01 | F27: 353.73 | G27: 369.77 | H27: 132.76 | I27: 310.72 | J27: 437.82 | K27: -129.42 | L27: 231.41 | M27: 206.53 | N27: 206.53
A28: Other Loans & Advances (Public Sector Enterprises, Statutory Bodies etc.) | B28: 14085.64 | C28: 15167 | D28: 29940.04 | E28: 27997.38 | F28: 57161.32 | G28: 15448.4 | H28: 2891.53 | I28: 13505.45 | J28: 6941.61 | K28: 16369.81 | L28: 17670.53 | M28: 55538.3 | N28: 57314.4
A29: TOTAL - RECOVERIES OF LOANS AND ADVANCES | B29: 24549 | C29: 26546.7 | D29: 41869.8 | E29: 40971.1 | F29: 70639.16 | G29: 30256.94 | H29: 18647.18 | I29: 29923.16 | J29: 24948.1 | K29: 36272.65 | L29: 116973.62 | M29: 199854.01 | N29: 146750.01
A31: C. MISCELLANEOUS CAPITAL RECEIPTS | B31: 29367.89 | C31: 37739.85 | D31: 42131.69 | E31: 47742.55 | F31: 100048.45 | G31: 94979.05 | H31: 50349.29 | I31: 37896.96 | J31: 14638.22 | K31: 46034.89 | L31: 45280.68 | M31: 36012.43 | N31: 47000
A32: TOTAL CAPITAL ACCOUNT RECEIPTS | B32: 4048883.1 | C32: 4282482.8 | D32: 4400951.2 | E32: 6222850.2 | F32: 6724689.2 | G32: 6883718.4 | H32: 7370383.5 | I32: 8230730.1 | J32: 8288738 | K32: 8947200.1 | L32: 9322304.2 | M32: 9929531.9 | N32: 10760099
A33: REVENUE RECEIPTS | B33: 1217798.8 | C33: 1328909 | D33: 1436160.2 | E33: 1615988 | F33: 1691143.1 | G33: 1806462.9 | H33: 1948083.5 | I33: 1864513.5 | J33: 2436421.5 | K33: 2713267.2 | L33: 3088174.6 | M33: 3485869.3 | N33: 3835268.5
A34: TOTAL-CONSOLIDATED FUND OF INDIA RECEIPTS | B34: 5266681.9 | C34: 5611391.8 | D34: 5837111.4 | E34: 8446838.5 | F34: 8415832.3 | G34: 8690181.3 | H34: 9318467 | I34: 10095244 | J34: 10725159 | K34: 11660467 | L34: 12410479 | M34: 13415401 | N34: 14595367

Sheet capital disbursements
A1: STATEMENT I - CONSOLIDATED FUND OF INDIA - CAPITAL ACCOUNT - DISBURSEMENTS
A2: Categories | B2: Actuals 2013-2014 | C2: Actuals 2014-2015 | D2: Actuals 2015-2016 | E2: Actuals 2016-2017 | F2: Actuals 2017-2018 | G2: Actuals 2018-2019 | H2: Actuals 2019-2020 | I2: Actuals 2020-2021 | J2: Actuals 2021-2022 | K2: Actuals 2022-2023 | L2: Actuals 2023-2024 | M2: Revised Estimates 2024-2025 | N2: Budget Estimates 2025-2026
A3: A. CAPITAL ACCOUNT OF GENERAL SERVICES | B3: 87900.22 | C3: 89995.26 | D3: 91462.26 | E3: 99183.05 | F3: 106352.76 | G3: 112921.39 | H3: 124807.42 | I3: 142745.65 | J3: 153776.9 | K3: 161187.49 | L3: 177487.65 | M3: 182591.24 | N3: 209088.88
A4: Audit | B4: ... | C4: ... | D4: 0 | E4: 0 | F4: … | G4: … | H4: … | I4: … | J4: … | K4: 0 | L4: 0 | M4: 142.29 | N4: 152.61
A5: Currency, Coinage and Mint | B5: ... | C5: ... | D5: 0 | E5: 0 | F5: 0 | G5: 186.27 | H5: 670.97 | I5: -1081.5 | J5: 1267.41 | K5: 1321.31 | L5: 272.38 | M5: 0 | N5: 0
A6: Other Fiscal Services | B6: 1085.01 | C6: 1160.37 | D6: 1558.76 | E6: 2538.05 | F6: 2232.3 | G6: 2336.54 | H6: 2588.45 | I6: 2508.71 | J6: 3258.93 | K6: 3305.58 | L6: 4969.77 | M6: 5825.53 | N6: 6348.1
A7: Police | B7: 6376.82 | C7: 5987.27 | D7: 9112.19 | E7: 8896.12 | F7: 10583.6 | G7: 9561.07 | H7: 8991.09 | I7: 4999.24 | J7: 7269.11 | K7: 8258.35 | L7: 9830.94 | M7: 10132.42 | N7: 15811.1
A8: Stationery and Printing | B8: 4.72 | C8: 9.66 | D8: ... | E8: 1.61 | F8: 0.33 | G8: 0 | H8: 0 | I8: ... | J8: 9.12 | K8: 1.2 | L8: 26.5 | M8: 38.69 | N8: 66.76
A9: Public Works | B9: 1315.07 | C9: 945.21 | D9: 821.47 | E9: 1368.24 | F9: 1586.8 | G9: 1218.1 | H9: 1270.92 | I9: 1585.27 | J9: 2682.67 | K9: 3885.87 | L9: 3721.23 | M9: 3876.17 | N9: 4661.49
A10: Other Administrative Services | B10: 6.64 | C10: 33.72 | D10: 10.36 | E10: 10.32 | F10: 1519.22 | G10: 4398.5 | H10: 220.73 | I10: 427.19 | J10: 1267.13 | K10: 1374.41 | L10: 3215.96 | M10: 898.17 | N10: 932.3
A11: Miscellaneous General Services | B11: -13.09 | C11: -27.95 | D11: 1.16 | E11: -2.21 | F11: -14.73 | G11: -9.68 | H11: -27.17 | I11: 1.82 | J11: 35.56 | K11: 100.76 | L11: 1194.59 | M11: 2177.97 | N11: 1116.52
A12: Defence Services | B12: 79125.05 | C12: 81886.98 | D12: 79958.32 | E12: 86370.92 | F12: 90445.24 | G12: 95230.59 | H12: 111092.43 | I12: 134304.92 | J12: 137986.97 | K12: 142940.01 | L12: 154256.28 | M12: 159500 | N12: 180000
A14: B. CAPITAL ACCOUNT OF SOCIAL SERVICES | B14: 3386.56 | C14: 4347.51 | D14: 4903.24 | E14: 4537.33 | F14: 8749.6 | G14: 9148.85 | H14: 9492.19 | I14: 7109.9 | J14: 9445.11 | K14: 12166.45 | L14: 8587.45 | M14: 11503.31 | N14: 11186.3
A15: Education, Sports, Art and Culture | B15: 38.19 | C15: 24.06 | D15: 56.53 | E15: 56.29 | F15: 316.3 | G15: 2358 | H15: 2215.89 | I15: 225.95 | J15: 51.91 | K15: 75.98 | L15: 67.17 | M15: 193.95 | N15: 197.68
A16: Medical and Public Health | B16: 1203.33 | C16: 821.78 | D16: 855.89 | E16: 1222.63 | F16: 3075.88 | G16: 2345.33 | H16: 1640.21 | I16: 3578.23 | J16: 3117.25 | K16: 3029.15 | L16: 1966.66 | M16: 2462.11 | N16: 3420.75
A17: Family Welfare | B17: ... | C17: ... | D17: 0.01 | E17: 0.09 | F17: 3.19 | G17: 11.61 | H17: 8.94 | I17: 3.99 | J17: 3.7 | K17: 2.14 | L17: 3.43 | M17: 3.91 | N17: 7.28
A18: Housing | B18: 811.44 | C18: 947.44 | D18: 932.41 | E18: 978.21 | F18: 1264.78 | G18: 1094.72 | H18: 962.62 | I18: 1132.13 | J18: 1448.68 | K18: 1794.16 | L18: 1497.36 | M18: 2219.33 | N18: 2019.73
A19: Urban Development | B19: 885 | C19: 1662.78 | D19: 2432.96 | E19: 1433.2 | F19: 3248.77 | G19: 2441 | H19: 3713.06 | I19: 1720.85 | J19: 4359.69 | K19: 6799.31 | L19: 4470.44 | M19: 6174.73 | N19: 4990.76
A20: Information and Publicity | B20: 21.45 | C20: 29.8 | D20: 21.51 | E20: 44.45 | F20: 11.24 | G20: 9.28 | H20: 4.29 | I20: 6.32 | J20: 21.09 | K20: 25.65 | L20: 37.55 | M20: 61.87 | N20: 43.79
A21: Welfare of Scheduled Castes, Scheduled Tribes , Other Backward Classes and Minorities | B21: 329.97 | C21: 762.1 | D21: 445.43 | E21: 528.08 | F21: 498.28 | G21: 507.44 | H21: 695.05 | I21: 210.06 | J21: 195.08 | K21: 224.09 | L21: 148.41 | M21: 30.65 | N21: 30.66
A22: Social Security and Welfare | B22: 32.55 | C22: 36.58 | D22: 54.25 | E22: 60 | F22: 46.05 | G22: 50.99 | H22: 1.15 | I22: 0.48 | J22: 0 | K22: 0 | L22: 0 | M22: 0 | N22: 0
A23: other Social Services | B23: 64.63 | C23: 62.97 | D23: 104.25 | E23: 214.38 | F23: 285.11 | G23: 330.48 | H23: 250.98 | I23: 231.89 | J23: 247.71 | K23: 215.97 | L23: 396.43 | M23: 356.76 | N23: 475.65
A25: C. CAPITAL ACCOUNT OF ECONOMIC SERVICES | B25: 76248.11 | C25: 76302.42 | D25: 180796.24 | E25: 144127.34 | F25: 207697.78 | G25: 275851.86 | H25: 252001.86 | I25: 191145.47 | J25: 371338.6 | K25: 447586.13 | L25: 617034.53 | M25: 653215.76 | N25: 731222.48
A26: (a) Capital Account of Agriculture and allied activities | B26: 817.64 | C26: 418.43 | D26: 416.88 | E26: 1472.31 | F26: 3938.97 | G26: 2709.9 | H26: 3294.04 | I26: 2291.64 | J26: 8638.56 | K26: 3381.29 | L26: 274.96 | M26: 279.67 | N26: 284.11
A27: Crop Husbandry | B27: 18.94 | C27: 13.73 | D27: 19.97 | E27: 12.16 | F27: 16.69 | G27: 9.81 | H27: 12.65 | I27: 21.8 | J27: 11.46 | K27: 8.1 | L27: 21.13 | M27: 92.03 | N27: 66.83
A28: Soil and Water Conservation | B28: 0.05 | C28: ... | E28: … | F28: … | G28: … | H28: … | I28: … | J28: … | K28: 0 | L28: 4.51 | M28: 4.25 | N28: 1.75
A29: Animal Husbandry | B29: 4.94 | C29: 7.75 | D29: 5.16 | E29: 5.71 | F29: 5.37 | G29: 5.35 | H29: 5.47 | I29: 3.52 | J29: 2.21 | K29: 13.45 | L29: 15.24 | M29: 52.21 | N29: 105.75
A30: Dairy Development | B30: 0.83 | C30: 0.97 | D30: 0.93 | E30: 0 | F30: 0 | G30: 0 | H30: 0.21 | I30: ... | J30: 0 | K30: 0 | L30: 0.03 | M30: 22.1 | N30: 2.8
A31: Fisheries | B31: 3.4 | C31: 1.39 | D31: 1.28 | E31: 2.29 | F31: 2.63 | G31: 2.39 | H31: 3.45 | I31: 4.69 | J31: 11.17 | K31: 2.28 | L31: 3.56 | M31: 7.75 | N31: 20.57
A32: Forestry and Wild Life | B32: 3.03 | C32: 5.01 | D32: 3.68 | E32: 14.62 | F32: 9.05 | G32: 15.1 | H32: 16.23 | I32: 17.81 | J32: 18.99 | K32: 26 | L32: 37.64 | M32: 45.48 | N32: 61.06
A33: Food Storage and Warehousing | B33: 3.49 | C33: 88.92 | D33: 70.86 | E33: 31.39 | F33: 24.56 | G33: 568.28 | H33: 1054.52 | I33: 1043.82 | J33: 2509.3 | K33: 1970.46 | L33: 189.35 | M33: 49.25 | N33: 20.77
A34: Investments in Agricultural Financial Institutions | B34: 782.78 | C34: 300 | D34: 315 | E34: 1405.5 | F34: 3880 | G34: 2108 | H34: 2200.51 | I34: 1200 | J34: 6084 | K34: 1361 | L34: 0 | M34: 0 | N34: 0.02
A35: Other Agricultural Programmes | B35: 0.18 | C35: 0.66 | D35: ... | E35: 0.64 | F35: 0.67 | G35: 0.97 | H35: 1 | I35: … | J35: 1.43 | K35: 0 | L35: 3.5 | M35: 6.6 | N35: 4.56
A36: (j) Capital Account of Rural Development | B36: … | C36: … | D36: … | E36: … | F36: … | G36: … | H36: … | I36: … | J36: 0 | K36: 0 | L36: 1.5 | M36: 21.04 | N36: 12.4
A37: Other Rural Development Programmes | B37: … | C37: … | D37: … | E37: … | F37: … | G37: … | H37: … | I37: … | J37: 0 | K37: 0 | L37: 1.5 | M37: 21.04 | N37: 12.4
A38: (b) Capital Account of Special Areas Programmes | B38: 83.68 | C38: 101.94 | D38: 257.91 | E38: 384.02 | F38: 202.36 | G38: 91.51 | H38: 579.6 | I38: 288.35 | J38: 621.89 | K38: 284.28 | L38: 977.16 | M38: 24495.07 | N38: 27979.68
A39: North Eastern Areas | B39: 83.68 | C39: 101.94 | D39: 257.91 | E39: 384.02 | F39: 202.36 | G39: 91.51 | H39: 579.6 | I39: 288.35 | J39: 621.89 | K39: 284.28 | L39: 977.16 | M39: 24495.07 | N39: 27979.68
A40: (c) Capital account of Irrigation and Flood Control | B40: 9.23 | C40: 17.04 | D40: 89.79 | E40: 82.14 | F40: 276.58 | G40: 267.23 | H40: 259.31 | I40: 133.07 | J40: 159.27 | K40: 138.4 | L40: 179.81 | M40: 241.32 | N40: 486.27
A41: Major and Medium Irrigation | B41: ... | C41: 1.29 | D41: 16.56 | E41: 24.5 | F41: 47.7 | G41: 35.28 | H41: 56.41 | I41: 47.71 | J41: 55.44 | K41: 58.22 | L41: 53.03 | M41: 88.88 | N41: 64.97
A42: Minor Irrigation | B42: 3.43 | C42: 3.55 | D42: 62.91 | E42: 47.81 | F42: 200.15 | G42: 214.42 | H42: 185.14 | I42: 77.23 | J42: 98.28 | K42: 79.51 | L42: 125.88 | M42: 150.54 | N42: 419.42
A43: Flood Control Projects | B43: 5.8 | C43: 12.2 | D43: 10.32 | E43: 9.83 | F43: 28.73 | G43: 17.53 | H43: 17.76 | I43: 8.13 | J43: 5.55 | K43: 0.67 | L43: 0.9 | M43: 1.9 | N43: 1.88
A44: (d) Capital Account of Energy | B44: 525.47 | C44: 708.59 | D44: 1944.07 | E44: 4533.65 | F44: 2448.52 | G44: 3817.32 | H44: 1374 | I44: 3019.2 | J44: 3519.85 | K44: 2082.82 | L44: 6999.23 | M44: 5977.11 | N44: 10646.24
A45: Power Projects | B45: 426.13 | C45: 437.46 | D45: 696.55 | E45: 2072.02 | F45: 1316.51 | G45: 1641.61 | H45: 773.49 | I45: 556.24 | J45: 596.56 | K45: 2069.35 | L45: 4011.35 | M45: 4984.2 | N45: 4017.24
A46: Petroleum | B46: ... | C46: ... | D46: 1153 | E46: 2451 | F46: 1131.01 | G46: 2158.32 | H46: 529.54 | I46: 2313 | J46: 347.31 | K46: 0 | L46: 2979.68 | M46: 987.91 | N46: 6624
A47: Coal and Lignite | B47: ... | C47: 176.13 | D47: ... | E47: ... | F47: ... | G47: ... | H47: ... | I47: ... | J47: ...
A48: New and Renewable Energy | B48: 99.34 | C48: 95 | D48: 94.52 | E48: 10.63 | F48: 1 | G48: 17.39 | H48: 70.97 | I48: 149.96 | J48: 2575.98 | K48: 13.47 | L48: 8.2 | M48: 5 | N48: 5
A49: (e) Capital Account of Industry and Minerals | B49: 3225.76 | C49: 4011.18 | D49: 3624.24 | E49: 4135.05 | F49: 4298.06 | G49: 8526 | H49: 12113.77 | I49: 5212.24 | J49: 6505.58 | K49: 6592.02 | L49: 6708.31 | M49: 12870.32 | N49: 12167.36
A50: Village and Small Industries | B50: 81.63 | C50: 9.51 | D50: 75.49 | E50: 179.39 | F50: 8.98 | G50: 23.34 | H50: 52 | I50: 71.72 | J50: 237.69 | K50: 436.42 | L50: 609.85 | M50: 570.85 | N50: 661.23
A51: Iron and Steel Industries | B51: … | C51: … | D51: … | E51: … | F51: … | G51: … | H51: … | I51: … | J51: … | K51: … | L51: 0 | M51: 7283.01 | N51: 2995
A52: Non-Ferrous Mining and Metallurgical Industries | B52: 344.96 | C52: 32.49 | D52: 51.81 | E52: 36.29 | F52: 84.85 | G52: 73.34 | H52: 81.39 | I52: 51.81 | J52: 52.84 | K52: 58.22 | L52: 75.27 | M52: 45.22 | N52: 78.44
A53: Chemical and Pharmaceutical Industries | B53: … | C53: … | D53: … | E53: … | F53: … | G53: … | H53: … | I53: … | J53: … | K53: 0 | L53: 0 | M53: 0 | N53: 0
A54: Engineering Industries | B54: 248.9 | C54: … | D54: … | E54: 1063.59 | F54: -49.22 | G54: … | H54: 0 | I54: … | J54: 0 | K54: 0 | L54: 91.64 | M54: 49.86 | N54: 0.05
A55: Telecommunication and Electronic Industries | B55: 17.94 | C55: 225.22 | D55: 56.08 | E55: 86.25 | F55: 400.04 | G55: 176.32 | H55: 183.85 | I55: 225.54 | J55: 210.09 | K55: 319.11 | L55: 493.07 | M55: 226.27 | N55: 287.96
A56: Consumer Industries | B56: 109.6 | C56: 73 | D56: 113.88 | E56: 0 | F56: 10 | G56: 49.54 | H56: 181.05 | I56: 92.95 | J56: 78.41 | K56: 0 | L56: 0 | M56: 0.02 | N56: 0.02
A57: Atomic Energy Industries | B57: 1322.73 | C57: 1710.76 | D57: 2026.97 | E57: 2266.95 | F57: 2647.27 | G57: 2400.75 | H57: 3028.01 | I57: 2492.68 | J57: 3398.72 | K57: 3561.13 | L57: 3294.01 | M57: 2808.5 | N57: 2456.18
A58: Other Industries | B58: ... | C58: 0.2 | D58: 0.01 | E58: 2.58 | F58: 496.14 | G58: 702.71 | H58: 1089.87 | I58: 777.54 | J58: 1677.83 | K58: 1717.14 | L58: 1644.47 | M58: 1386.59 | N58: 5688.47
A59: Other Industries and Minerals | B59: 1100 | C59: 1960 | D59: 1300 | E59: 500 | F59: 700 | G59: 5100 | H59: 7497.6 | I59: 1500 | J59: 850 | K59: 500 | L59: 500 | M59: 500 | N59: 0.01
A60: (f) Capital Account of Transport | B60: 48305.1 | C60: 52768.66 | D60: 68249.62 | E60: 92084.8 | F60: 99016.57 | G60: 126787.65 | H60: 138894.7 | I60: 122449.35 | J60: 297124.32 | K60: 370536.16 | L60: 514475.22 | M60: 512183.46 | N60: 512582.76
A61: Indian Railways - Commercial Lines | B61: 26124.52 | C61: 29199.79 | D61: 35007.87 | E61: 45231.63 | F61: 43285.27 | G61: 52102.61 | H61: 67839.86 | I61: 29909.58 | J61: 117231.73 | K61: 159169.22 | L61: 242537.91 | M61: 252337.84 | N61: 251950.81
A62: Indian Railways - Strategic Lines | B62: 947.88 | C62: 921.37 | E62: 0 | F62: 132.28 | G62: 735.06 | H62: 1.9 | I62: 16.11 | J62: 38.81 | K62: 86.93 | L62: 110.55 | M62: 39.46 | N62: 49.19
A63: Ports and Light Houses | B63: 147.76 | C63: 185.65 | D63: 189.76 | E63: 316.71 | F63: 171.77 | G63: 177.77 | H63: 241.61 | I63: 159.99 | J63: 137.89 | K63: 124.15 | L63: 122.1 | M63: 40.01 | N63: 56
A64: Shipping | B64: 61.41 | C64: 3.03 | D64: 2.31 | E64: 7.59 | F64: 2.88 | G64: -22.52 | H64: 18.24 | I64: 9.11 | J64: 9.23 | K64: 10.94 | L64: 13.72 | M64: 38.12 | N64: 27.5
A65: Civil Aviation | B65: 6054.63 | C65: 5814.94 | D65: 3361.02 | E65: 2709.27 | F65: 1836.84 | G65: 3975.87 | H65: 21.36 | I65: 35.9 | J65: 62421.99 | K65: 75.44 | L65: 741.31 | M65: 88.05 | N65: 45
A66: Roads and Bridges | B66: 14890.65 | C66: 16572.39 | D66: 29636.4 | E66: 43774.48 | F66: 53524.63 | G66: 69760.86 | H66: 70713.65 | I66: 92293.6 | J66: 116787.77 | K66: 210495.94 | L66: 269865.27 | M66: 258853.05 | N66: 259117.56
A67: Road Transport | B67: ... | C67: ... | D67: ... | E67: 8.09 | F67: 2.28 | G67: 8 | H67: 8 | I67: 5.5 | J67: 5 | K67: 0 | L67: 30 | M67: 30 | N67: 30
A68: Inland Water Transport | B68: … | C68: … | D68: … | E68: … | F68: … | G68: … | H68: … | I68: ... | J68: 467.54 | K68: 544.31 | L68: 1010.5 | M68: 707.61 | N68: 1254.81
A69: Other Transport Services | B69: 78.25 | C69: 71.49 | D69: 52.26 | E69: 37.03 | F69: 60.62 | G69: 50 | H69: 50.08 | I69: 19.56 | J69: 24.36 | K69: 29.23 | L69: 43.86 | M69: 49.32 | N69: 51.89
A70: (g) Capital Account of Communications | B70: 1375.64 | C70: 1480.74 | D70: 3548.16 | E70: 3477.05 | F70: 4507.27 | G70: 2570.5 | H70: 5220.05 | I70: 4928.53 | J70: 3941.81 | K70: 55618.29 | L70: 60517.07 | M70: 75048.57 | N70: 50193.51
A71: Postal Services | B71: 268.97 | C71: 172.96 | D71: 335.18 | E71: 229.45 | F71: 638.26 | G71: 511.27 | H71: 395.56 | I71: 677.42 | J71: 685.55 | K71: 1076.67 | L71: 1136.89 | M71: 893.88 | N71: 859.89
A72: Satellite System | B72: 890.14 | C72: 930.79 | D72: 933.17 | E72: 0 | F72: 0 | G72: 0 | H72: 0 | I72: 0 | J72: 0 | K72: 0
A73: Other Communication Services | B73: 216.53 | C73: 376.99 | D73: 2279.81 | E73: 3247.6 | F73: 3869.01 | G73: 2059.23 | H73: 4824.49 | I73: 4251.11 | J73: 3256.26 | K73: 54541.62 | L73: 59380.18 | M73: 74154.69 | N73: 49333.62
A74: (h) Capital Account of Science Technology and Environment | B74: 3078.35 | C74: 3186.36 | D74: 4036.82 | E74: 5228.65 | F74: 5373.08 | G74: 7294.96 | H74: 9221.6 | I74: 6029.43 | J74: 9995.41 | K74: 7791.68 | L74: 7157.09 | M74: 6397.83 | N74: 8123.9
A75: Atomic Energy Research | B75: 1460.51 | C75: 1570.33 | D75: 1861.99 | E75: 1590.33 | F75: 1518.35 | G75: 1643.23 | H75: 1956.96 | I75: 1283.15 | J75: 3014.21 | K75: 3426.01 | L75: 2616.44 | M75: 1408.07 | N75: 1490.81
A76: Space Research | B76: 1550.92 | C76: 1520.07 | D76: 2110.64 | E76: 3587.07 | F76: 3796.05 | G76: 5532.64 | H76: 7181.02 | I76: 4633.96 | J76: 6901.86 | K76: 4253.43 | L76: 4396.75 | M76: 4728.37 | N76: 6103.63
A77: Oceanographic Research | B77: 5.24 | C77: 0.26 | D77: 1.9 | E77: 7.89 | F77: 9.96 | G77: 13.16 | H77: 11.23 | I77: 5.85 | J77: 7.15 | K77: 15.81 | L77: 55.23 | M77: 135 | N77: 339.6
A78: Other Scientific and Environmental Research | B78: 61.68 | C78: 95.7 | D78: 62.29 | E78: 43.36 | F78: 48.72 | G78: 105.93 | H78: 72.39 | I78: 106.47 | J78: 72.19 | K78: 96.43 | L78: 88.67 | M78: 126.39 | N78: 189.86
A79: (i) Capital Account of General Economic Services | B79: 18827.24 | C79: 13609.48 | D79: 98628.75 | E79: 32729.67 | F79: 87636.37 | G79: 123786.79 | H79: 81044.79 | I79: 46793.66 | J79: 40831.91 | K79: 1161.19 | L79: 19744.18 | M79: 15701.37 | N79: 108746.25
A80: Tourism | B80: 2 | C80: 1.7 | D80: 0.62 | E80: 0 | F80: … | G80: … | H80: … | I80: … | J80: … | K80: 0 | L80: 0 | M80: 4.49 | N80: 6.13
A81: Foreign Trade and Export Promotion | B81: 849.64 | C81: 274.21 | D81: 49.66 | E81: 60 | F81: 62.5 | G81: -5.03 | H81: -12.57 | I81: -6.06 | J81: -7.24 | K81: 0 | L81: 2.61 | M81: 2.99 | N81: 3
A82: Meteorology | B82: 77.07 | C82: 51.72 | D82: 91.01 | E82: 66.59 | F82: 45.43 | G82: 71.24 | H82: 93.98 | I82: 63.79 | J82: 92.39 | K82: 72.48 | L82: 93.1 | M82: 1029.6 | N82: 535.47
A83: Investments in General Financial and Trading Institutions | B83: 16100 | C83: 7090 | D83: 25700.04 | E83: 26422.18 | F83: 90175.35 | G83: 109466.29 | H83: 75721.28 | I83: 36042.72 | J83: 33488.14 | K83: 3489.34 | L83: 11958.48 | M83: 3310 | N83: 4500.02
A84: Investments in International Financial Institutions | B84: 844.06 | C84: 5186.1 | D84: 71636.88 | E84: 5673.61 | F84: -2905.12 | G84: 13971.16 | H84: 5001.12 | I84: 10385.01 | J84: 6968.4 | K84: -2601.34 | L84: 7309.77 | M84: 1539.22 | N84: 61291.71
A85: Other General Economic Services | B85: 954.47 | C85: 1005.75 | D85: 1150.54 | E85: 507.29 | F85: 258.21 | G85: 283.13 | H85: 240.98 | I85: 308.2 | J85: 290.22 | K85: 200.71 | L85: 380.22 | M85: 9815.07 | N85: 42409.92
A86: Disbursements of Union Territories without Legislature | B86: 1309.58 | C86: 1439.87 | D86: 1704.6 | E86: 1624.1 | F86: 2315.85 | G86: 1600.64 | H86: 1442.64 | I86: 1947.76 | J86: 3579.62 | K86: 3817.18 | L86: 4070.71 | M86: 4570.91 | N86: 4747.65
A87: TOTAL - CAPITAL EXPENDITURE OUTSIDE THE REVENUE ACCOUNT | B87: 168844.47 | C87: 172085.06 | D87: 278866.34 | E87: 249471.82 | F87: 325115.99 | G87: 399522.74 | H87: 387744.11 | I87: 342948.78 | J87: 538140.23 | K87: 624757.25 | L87: 807180.34 | M87: 851881.22 | N87: 956245.31
A88: PUBLIC DEBT
A89: Internal Debt of Central Government
A90: Market Loans Less: Amount Met from GST Compensation Fund | B90: 95006.57 | C90: 138924.68 | D90: 216250.08 | E90: 275013.54 | F90: 137271.69 | G90: 148265.4 | H90: 388835.42 | I90: 227208.32 | J90: 264335.41 | K90: 312740.47 | L90: 543639.77 | M90: 361422.24 | N90: 395666.06
A91: Buyback / Switching | B91: 46589.54 | C91: 45311.19 | D91: 3000.3 | E91: 0 | F91: 99630.07 | G91: 28058.99 | H91: 12000 | I91: 153417.57 | J91: 168410.69 | K91: 105489.62 | L91: 0 | M91: 235158.64 | N91: 250000
A92: 14 days Treasury Bills | B92: 2183501.9 | C92: 2217261.9 | D92: 2414470.1 | E92: 3180676 | F92: 3796169.2 | G92: 3599384.3 | H92: 3322613.1 | I92: 3695125 | J92: 4421317.9 | K92: 4871057.4 | L92: 4785271.9 | M92: 5750288.2 | N92: 6030452.7
A93: 91 days Treasury Bills | B93: 559423.26 | C93: 667112.12 | D93: 682773.48 | E93: 690582.15 | F93: 742174.08 | G93: 706707.7 | H93: 649072.75 | I93: 732774.82 | J93: 802464.83 | K93: 739748.84 | L93: 624263.82 | M93: 687745.05 | N93: 606191.25
A94: 182 days Treasury Bills | B94: 125298.91 | C94: 146688.24 | D94: 161719.01 | E94: 166405.74 | F94: 183981.05 | G94: 225089.11 | H94: 283335.51 | I94: 507349.73 | J94: 394426.49 | K94: 496815.33 | L94: 555209.29 | M94: 446683.21 | N94: 484082.34
A95: 364 days Treasury Bills | B95: 87900.22 | C95: 143004.76 | D95: 143152.18 | E95: 154033.2 | F95: 142525.74 | G95: 159685 | H95: 208896 | I95: 217670 | J95: 458240 | K95: 407796.43 | L95: 445283.5 | M95: 457486.99 | N95: 360809.92
A96: Cash Management Bills | B96: 107195 | C96: 10000 | D96: ... | E96: 0 | F96: 150000 | G96: 190000 | H96: 220000 | I96: 160000 | J96: 0 | K96: 0 | L96: 0 | M96: 0 | N96: 50000
A97: Ways and Means Advances | B97: 1085.01 | C97: 316116 | D97: 83843 | E97: 163489 | F97: 480042 | G97: 955243 | H97: 1179582 | I97: 398990 | J97: 0 | K97: 57596 | L97: 199313 | M97: 55000 | N97: 500000
A98: Redemption of securities issued to International Financial Institutions | B98: … | C98: … | D98: 1888.38 | E98: 492.44 | F98: 7467.66 | G98: 7661.64 | H98: 5634.59 | I98: 10543.62 | J98: 3357.98 | K98: 5616.44 | L98: 3294.79 | M98: 7785.54 | N98: 7776.91
A99: Compensation and Other Bonds | B99: … | C99: … | D99: 5482.54 | E99: 5413.77 | F99: 624.85 | G99: 578.44 | H99: 273.65 | I99: 317.64 | J99: 3182.18 | K99: 14916.18 | L99: 23054.88 | M99: 1654.31 | N99: 3115.92
A100: Redemption of Securities issued to NSSF | B100: … | C100: … | D100: 1772.51 | E100: 5004 | F100: 6033.05 | G100: 13533.05 | H100: 22413.31 | I100: 42502.46 | J100: 86748.54 | K100: 137679.96 | L100: 232737.58 | M100: 340484.61 | N100: 279509.04
A101: Postal Life Insurance Fund | B101: … | C101: … | D101: … | E101: … | F101: … | G101: … | H101: … | I101: 4000 | J101: 7000 | K101: 9893.68 | L101: 0 | M101: 0 | N101: 0
A102: Gold Monetization Scheme | B102: … | C102: … | D102: … | E102: … | F102: … | G102: … | H102: 1.52 | I102: 9.29 | J102: 19.36 | K102: 19.9 | L102: 27.01 | M102: 132.08 | N102: 145.28
...
